{
  "metadata": {
    "code": "INM3513-009v1",
    "name": "AIoT應用工程師",
    "update_date": "",
    "version": "V1",
    "status": "最新版本",
    "source_file": "C:\\Users\\User\\Graph_RAG_test\\data\\raw_pdf\\AIoT應用工程師-職能基準.pdf"
  },
  "basic_info": {
    "category": "製造 / 生產管理資訊科技／網路規劃與建置管理資訊科技 / 軟體開發及程式設計科學、技術、工程、數學/工程及技術",
    "category_code": "MPMINMISDSET",
    "occupation": "科學及工程專業人員機械工程師電子工程師其他軟體、應用程式開發人員及分析師資料庫及網路專業人員電腦網路專業人員電腦網路及系統技術員",
    "occupation_code": "2121442152251925225233513",
    "industry": [
      "電信及資訊服務業／電腦程式設計、諮詢及相關服務業",
      "製造業 / 電子零組件製造業",
      "製造業 / 電腦、電子產品及光學製品製造業",
      "製造業 / 機械設備製造業",
      "製造業 / 產業用機械設備維修及安裝業"
    ],
    "industry_code": [
      "K62",
      "C26",
      "C27",
      "C29",
      "C34"
    ],
    "job_description": "依據產業應用需求，具備運用AIoT系統整合與應用能力，並且熟悉感測模組、通訊技術、邊緣設備與雲端平台之部署與串接。能依場域特性規劃適配的資料傳輸架構以整合必要的多通訊協定，實作資料擷取、格式轉換與視覺化呈現，並具備資訊安全意識與系統維運能力，協助場域導入、分析、善用感測數據達成數位化與智慧化應用目標。",
    "level": 4,
    "requirements": ""
  },
  "competency_tasks": [
    {
      "main_responsibility": "T1AIoT標準與應用趨勢研究",
      "task_id": "T1.1",
      "task_name": "蒐集國際及國內AIoT相關標準",
      "output": "AIoT相關軟硬體所具備之國際標準分析報告",
      "behaviors": [
        "能夠分析比較不同AIoT應用與所採用之產品（與其標準）優劣勢。"
      ],
      "knowledge": [
        "K01",
        "K02",
        "K03",
        "K04"
      ],
      "skills": [
        "S01",
        "S02",
        "S03"
      ],
      "level": 3
    },
    {
      "main_responsibility": "T2AIoT系統需求分析與解決方案設計",
      "task_id": "T2.1",
      "task_name": "客戶作業模式與流程分析",
      "output": "系統導入前後作業流程比較表、系統需求規劃書（含設備需求與系統功能清單）",
      "behaviors": [
        "系統導入前後之作業模式差異分析。",
        "辨識既有機/電/感測設備導入現況。",
        "能夠將新技術、產品、市場、AIoT標準規範等資訊，轉換為系統導入依據，並訂定出符合客戶需求的規格，或是制定全新的應用領域。"
      ],
      "knowledge": [
        "K07",
        "K08",
        "K09",
        "K10",
        "K11",
        "K05",
        "K06",
        "K12",
        "K13",
        "K14"
      ],
      "skills": [
        "S07",
        "S08",
        "S09",
        "S10",
        "S11",
        "S12"
      ],
      "level": 3
    },
    {
      "main_responsibility": "T3AIoT雲端與資料交換設計",
      "task_id": "T3.1",
      "task_name": "AIoT雲端服務模式評估",
      "output": "雲端服務模式分析比較表、資訊安全風險評估報告",
      "behaviors": [
        "有效掌握客戶軟體系統開發與維護能力，協助客戶了解不同的雲端服務特性，選用較佳開發方案。",
        "評估各系統元件採用加密、簽章、去識別化的程度與時機。",
        "確保物聯網資料不易遭受竄改，及提供資料不可否認性確認功能。",
        "企業導入安全認證（如ISO 27001，Security+等）之評估。"
      ],
      "knowledge": [
        "K07",
        "K17",
        "K18",
        "K19",
        "K20",
        "K21",
        "K22"
      ],
      "skills": [
        "S16",
        "S17",
        "S18",
        "S15",
        "S19"
      ],
      "level": 4
    },
    {
      "main_responsibility": "T3AIoT雲端與資料交換設計",
      "task_id": "T3.2",
      "task_name": "規劃AIoT資料交換架構與標準",
      "output": "AIoT資料識別與編碼原則文件、AIoT資料交換格式報告",
      "behaviors": [
        "協助客戶了解系統或設備之框架基礎與編碼規範。",
        "制定AIoT各層級元件資料交換格式與通訊方式，並兼顧系統或設備間的整合需求。"
      ],
      "knowledge": [
        "K23",
        "K24",
        "K25",
        "K04",
        "K21",
        "K26",
        "K27",
        "K28",
        "K29",
        "K30"
      ],
      "skills": [
        "S20",
        "S21",
        "S22",
        "S23",
        "S24",
        "S25"
      ],
      "level": 3
    },
    {
      "main_responsibility": "T4AIoT通訊及感測系統建置與測試",
      "task_id": "T4.1",
      "task_name": "AIoT通訊品質評估",
      "output": "通訊產品之讀取效能測試報告",
      "behaviors": [
        "針對通訊產品效能測試結果進行讀取效能分析並提出優化方案。",
        "協助客戶選擇適合之設備佈建場域，排除環境干擾因素影響使AIoT系統之讀取效能達最佳化。"
      ],
      "knowledge": [
        "K04",
        "K32",
        "K33",
        "K03",
        "K34",
        "K35"
      ],
      "skills": [
        "S29",
        "S30",
        "S31",
        "S32"
      ],
      "level": 3
    },
    {
      "main_responsibility": "T5AIoT系統更新與維護",
      "task_id": "T5.1",
      "task_name": "AIoT功能新增與系統升級",
      "output": "新增功能規格書、系統導入與升級建置計畫書",
      "behaviors": [
        "能於既有系統架構中增加AIoT新功能。",
        "有效規劃AIoT系統導入與升級步驟，確保新舊系統能無縫接軌。",
        "評估與採用各式備援與高可靠性（HA）機制，定義系統服務層級協議（SLA）。"
      ],
      "knowledge": [
        "K15",
        "K16",
        "K38",
        "K39"
      ],
      "skills": [
        "S10",
        "S11",
        "S28",
        "S37"
      ],
      "level": 4
    },
    {
      "main_responsibility": "T6機器聯網通訊與控制系統整合應用",
      "task_id": "T6.1",
      "task_name": "分析與規劃機器聯網解決方案",
      "output": "設備清冊與現況評估報告、機器聯網通訊架構與整合建議書",
      "behaviors": [
        "能辨識並盤點現場控制器、感測器、I/O模組等設備資源，釐清其介面與資料交換方式。",
        "瞭解公司機器聯網策略、現況與資源投入程度，規劃AIoT導入順序與方案，並制定與選用合適的通訊協定與標準。"
      ],
      "knowledge": [
        "K09",
        "K14",
        "K04",
        "K10",
        "K13",
        "K41"
      ],
      "skills": [
        "S23",
        "S33",
        "S01",
        "S09",
        "S10",
        "S39",
        "S40"
      ],
      "level": 4
    },
    {
      "main_responsibility": "T6機器聯網通訊與控制系統整合應用",
      "task_id": "T6.2",
      "task_name": "識別數據與制定擷取、傳輸儲存與安全管理方式",
      "output": "資料識別與擷取規劃書、資料安全傳輸與儲存規劃方案",
      "behaviors": [
        "評估機器資料擷取自動化可行方案，制定擷取方式、頻率與結構化欄位。",
        "制定資料擷取所使用的通訊與傳輸方式，規劃全程安全管理機制，包含擷取不落地、傳輸加密、安全儲存機制、資料調用安全稽核方式。"
      ],
      "knowledge": [
        "K04",
        "K09",
        "K13",
        "K24",
        "K26",
        "K28",
        "K29",
        "K30",
        "K21",
        "K27",
        "K41",
        "K42",
        "K43"
      ],
      "skills": [
        "S18",
        "S22",
        "S39",
        "S33",
        "S40",
        "S19",
        "S41"
      ],
      "level": 4
    },
    {
      "main_responsibility": "T6機器聯網通訊與控制系統整合應用",
      "task_id": "T6.3",
      "task_name": "建置機器聯網感測、通訊與應用",
      "output": "整合與建置機電聯網感測與傳輸機制、多系統資料共享應用與視覺化設計文件、建置與擴大機器聯網應用",
      "behaviors": [
        "能整合異質設備與資料來源，設計跨系統通訊與資料接軌方案。",
        "能建構應用層儀表板或資料展示介面，支援資料即時監控、預警或生產效率分析。",
        "依據企業聯網策略與導入規劃，建置多元機器聯網應用機制，並逐步擴大應用範圍，達成預防問題發生、提升人機稼動、產能最佳化等目的。同時制定方案維運計劃，提出完整的系統失效分析與故障排除對策。"
      ],
      "knowledge": [
        "K10",
        "K28",
        "K29",
        "K30",
        "K35",
        "K41",
        "K44",
        "K45",
        "K16",
        "K18",
        "K19",
        "K20",
        "K38"
      ],
      "skills": [
        "S18",
        "S23",
        "S32",
        "S33",
        "S35",
        "S40",
        "S25",
        "S26",
        "S27",
        "S28",
        "S07",
        "S09",
        "S30",
        "S38"
      ],
      "level": 5
    },
    {
      "main_responsibility": "T6機器聯網通訊與控制系統整合應用",
      "task_id": "T6.4",
      "task_name": "落實工控資安",
      "output": "產出工控資安風險管理規劃、導入與落實工控資安標準與防護機制",
      "behaviors": [
        "識別工控資安風險，評估工控資安成熟度。規劃機器與感測數據之安全使用管理辦法，包含認證、授權、通訊加密與稽核方式。",
        "完成工控資安檢測與監控，達成工控資安標準及規範，例如IEC62443、IEC TR63283-3:2022、Machinery。"
      ],
      "knowledge": [
        "K15",
        "K18",
        "K21",
        "K22",
        "K43",
        "K02",
        "K04",
        "K45"
      ],
      "skills": [
        "S01",
        "S19",
        "S37",
        "S41",
        "S09",
        "S25",
        "S40"
      ],
      "level": 5
    }
  ],
  "competency_knowledge": [
    {
      "code": "K01",
      "name": "AIoT系統基本架構",
      "category": "知識"
    },
    {
      "code": "K02",
      "name": "AIoT相關國際標準",
      "category": "知識"
    },
    {
      "code": "K03",
      "name": "基礎通訊原理",
      "category": "知識"
    },
    {
      "code": "K04",
      "name": "工業通訊標準",
      "category": "知識"
    },
    {
      "code": "K05",
      "name": "AIoT發展趨勢",
      "category": "知識"
    },
    {
      "code": "K06",
      "name": "AIoT應用案例",
      "category": "知識"
    },
    {
      "code": "K07",
      "name": "導入效益分析概念",
      "category": "知識"
    },
    {
      "code": "K08",
      "name": "作業原理",
      "category": "知識"
    },
    {
      "code": "K09",
      "name": "設備控制器與機構知識",
      "category": "知識"
    },
    {
      "code": "K10",
      "name": "機電整合",
      "category": "知識"
    },
    {
      "code": "K11",
      "name": "機器學習",
      "category": "知識"
    },
    {
      "code": "K12",
      "name": "五力分析",
      "category": "知識"
    },
    {
      "code": "K13",
      "name": "自動辨識與感測技術基礎知識（含感測器原理/趨勢）",
      "category": "知識"
    },
    {
      "code": "K14",
      "name": "控制系統與機器聯網平台概念",
      "category": "知識"
    },
    {
      "code": "K15",
      "name": "專案風險評估概念",
      "category": "知識"
    },
    {
      "code": "K16",
      "name": "專案管理知識",
      "category": "知識"
    },
    {
      "code": "K17",
      "name": "雲端技術與服務架構基礎",
      "category": "知識"
    },
    {
      "code": "K18",
      "name": "Dev-Ops相關知識",
      "category": "知識"
    },
    {
      "code": "K19",
      "name": "系統管理知識",
      "category": "知識"
    },
    {
      "code": "K20",
      "name": "網路管理知識",
      "category": "知識"
    },
    {
      "code": "K21",
      "name": "AIoT資訊安全對策",
      "category": "知識"
    },
    {
      "code": "K22",
      "name": "網路安全概論",
      "category": "知識"
    },
    {
      "code": "K23",
      "name": "AIoT識別編碼架構基礎觀念",
      "category": "知識"
    },
    {
      "code": "K24",
      "name": "AIoT識別與資料服務架構元件",
      "category": "知識"
    },
    {
      "code": "K25",
      "name": "AIoT識別編碼設計原則與應用",
      "category": "知識"
    },
    {
      "code": "K26",
      "name": "AIoT資料交換格式",
      "category": "知識"
    },
    {
      "code": "K27",
      "name": "網路及資料庫概論",
      "category": "知識"
    },
    {
      "code": "K28",
      "name": "I/O通訊原理",
      "category": "知識"
    },
    {
      "code": "K29",
      "name": "資料擷取、結構設計與儲存",
      "category": "知識"
    },
    {
      "code": "K30",
      "name": "多感測訊號源融合與同步機制",
      "category": "知識"
    },
    {
      "code": "K31",
      "name": "開源軟硬體與授權方式",
      "category": "知識"
    },
    {
      "code": "K32",
      "name": "無線通訊技術",
      "category": "知識"
    },
    {
      "code": "K33",
      "name": "天線設計基本原理",
      "category": "知識"
    },
    {
      "code": "K34",
      "name": "電磁學知識",
      "category": "知識"
    },
    {
      "code": "K35",
      "name": "信號調節技術",
      "category": "知識"
    },
    {
      "code": "K36",
      "name": "電子電路學基礎知識",
      "category": "知識"
    },
    {
      "code": "K37",
      "name": "嵌入式作業系統基礎知識",
      "category": "知識"
    },
    {
      "code": "K38",
      "name": "雲端備援與HA機制",
      "category": "知識"
    },
    {
      "code": "K39",
      "name": "雲端彈性擴展知識",
      "category": "知識"
    },
    {
      "code": "K40",
      "name": "程式設計基礎",
      "category": "知識"
    },
    {
      "code": "K41",
      "name": "通訊管理技術",
      "category": "知識"
    },
    {
      "code": "K42",
      "name": "雲端與平台架構應用",
      "category": "知識"
    },
    {
      "code": "K43",
      "name": "ICS/SCADA安全概論",
      "category": "知識"
    },
    {
      "code": "K44",
      "name": "軟體應用與開源技術",
      "category": "知識"
    },
    {
      "code": "K45",
      "name": "人機界面",
      "category": "知識"
    }
  ],
  "competency_skills": [
    {
      "code": "S01",
      "name": "資料搜集與分析能力",
      "category": "技能"
    },
    {
      "code": "S02",
      "name": "英文閱讀能力",
      "category": "技能"
    },
    {
      "code": "S03",
      "name": "瞭解判讀產品規格書能力",
      "category": "技能"
    },
    {
      "code": "S04",
      "name": "論壇與相關發表研讀能力",
      "category": "技能"
    },
    {
      "code": "S05",
      "name": "AIoT應用趨勢與需求分析能力",
      "category": "技能"
    },
    {
      "code": "S06",
      "name": "AIoT應用發展整合判斷能力",
      "category": "技能"
    },
    {
      "code": "S07",
      "name": "作業流程問題分析能力",
      "category": "技能"
    },
    {
      "code": "S08",
      "name": "流程最佳化",
      "category": "技能"
    },
    {
      "code": "S09",
      "name": "跨部門溝通與協調能力",
      "category": "技能"
    },
    {
      "code": "S10",
      "name": "需求規格書撰寫能力",
      "category": "技能"
    },
    {
      "code": "S11",
      "name": "專案提案簡報及計畫書撰寫能力",
      "category": "技能"
    },
    {
      "code": "S12",
      "name": "使用者操作介面設計能力",
      "category": "技能"
    },
    {
      "code": "S13",
      "name": "成本效益分析能力",
      "category": "技能"
    },
    {
      "code": "S14",
      "name": "專案風險分析能力",
      "category": "技能"
    },
    {
      "code": "S15",
      "name": "營運衝擊分析能力",
      "category": "技能"
    },
    {
      "code": "S16",
      "name": "雲端平台與中介軟體評估能力",
      "category": "技能"
    },
    {
      "code": "S17",
      "name": "應用層系統架構與導入策略",
      "category": "技能"
    },
    {
      "code": "S18",
      "name": "相關程式語言開發技能力",
      "category": "技能"
    },
    {
      "code": "S19",
      "name": "資訊安全評估與導入策略",
      "category": "技能"
    },
    {
      "code": "S20",
      "name": "應用層系統備援方案評估與導入策略",
      "category": "技能"
    },
    {
      "code": "S21",
      "name": "服務/產品導入標準化識別編碼規範之能力",
      "category": "技能"
    },
    {
      "code": "S22",
      "name": "資料格式設計能力",
      "category": "技能"
    },
    {
      "code": "S23",
      "name": "跨系統資料交換技術應用能力",
      "category": "技能"
    },
    {
      "code": "S24",
      "name": "RE",
      "category": "技能"
    },
    {
      "code": "S25",
      "name": "資訊可視化與預警技術應用",
      "category": "技能"
    },
    {
      "code": "S26",
      "name": "測試程序與工具",
      "category": "技能"
    },
    {
      "code": "S27",
      "name": "撰寫測試報告能力",
      "category": "技能"
    },
    {
      "code": "S28",
      "name": "系統備援方案評估與導入策略",
      "category": "技能"
    },
    {
      "code": "S29",
      "name": "無線頻譜量測技術",
      "category": "技能"
    },
    {
      "code": "S30",
      "name": "網路層系統備援方案評估與導入策略",
      "category": "技能"
    },
    {
      "code": "S31",
      "name": "網路層無線通訊實作能力",
      "category": "技能"
    },
    {
      "code": "S32",
      "name": "雜訊干擾防範處理",
      "category": "技能"
    },
    {
      "code": "S33",
      "name": "感知層感測器規格分析能力",
      "category": "技能"
    },
    {
      "code": "S34",
      "name": "AIoT輸出入裝置安裝與設定技術",
      "category": "技能"
    },
    {
      "code": "S35",
      "name": "信號濾波",
      "category": "技能"
    },
    {
      "code": "S36",
      "name": "信號放大",
      "category": "技能"
    },
    {
      "code": "S37",
      "name": "操作手冊撰寫能力",
      "category": "技能"
    },
    {
      "code": "S38",
      "name": "問題排除與系統維護規劃能力",
      "category": "技能"
    },
    {
      "code": "S39",
      "name": "通訊與設備技術應用能力",
      "category": "技能"
    },
    {
      "code": "S40",
      "name": "機器聯網應用技術",
      "category": "技能"
    },
    {
      "code": "S41",
      "name": "工控系統安全設計能力",
      "category": "技能"
    }
  ],
  "competency_attitudes": [],
  "chunks_for_rag": [
    {
      "id": "basic_info",
      "type": "基本資訊",
      "content": "職能基準：AIoT標準與應用趨\n代碼：INM3513-009v1\n版本：V1\n職類別：製造 / 生產管理資訊科技／網路規劃與建置管理資訊科技 / 軟體開發及程式設計科學、技術、工程、數學/工程及技術（代碼：MPMINMISDSET）\n職業別：科學及工程專業人員機械工程師電子工程師其他軟體、應用程式開發人員及分析師資料庫及網路專業人員電腦網路專業人員電腦網路及系統技術員（代碼：2121442152251925225233513）\n行業別：電信及資訊服務業／電腦程式設計、諮詢及相關服務業; 製造業 / 電子零組件製造業; 製造業 / 電腦、電子產品及光學製品製造業; 製造業 / 機械設備製造業; 製造業 / 產業用機械設備維修及安裝業（代碼：K62; C26; C27; C29; C34）\n基準級別：4\n工作描述：依據產業應用需求，具備運用AIoT系統整合與應用能力，並且熟悉感測模組、通訊技術、邊緣設備與雲端平台之部署與串接。能依場域特性規劃適配的資料傳輸架構以整合必要的多通訊協定，實作資料擷取、格式轉換與視覺化呈現，並具備資訊安全意識與系統維運能力，協助場域導入、分析、善用感測數據達成數位化與智慧化應用目標。\n建議條件：\n更新日期：",
      "metadata": {
        "code": "INM3513-009v1",
        "name": "AIoT標準與應用趨",
        "level": 4,
        "chunk_type": "overview"
      }
    },
    {
      "id": "task_T1.1",
      "type": "工作任務",
      "content": "主要職責：T1AIoT標準與應用趨勢研究\n任務編號：T1.1\n任務名稱：蒐集國際及國內AIoT相關標準\n職能級別：3\n工作產出：AIoT相關軟硬體所具備之國際標準分析報告\n\n行為指標：\n- 能夠分析比較不同AIoT應用與所採用之產品（與其標準）優劣勢。\n\n所需知識（4項）：\n- AIoT系統基本架構\n- AIoT相關國際標準\n- 基礎通訊原理\n- 工業通訊標準\n\n所需技能（3項）：\n- 資料搜集與分析能力\n- 英文閱讀能力\n- 瞭解判讀產品規格書能力",
      "metadata": {
        "task_id": "T1.1",
        "task_name": "蒐集國際及國內AIoT相關標準",
        "main_responsibility": "T1AIoT標準與應用趨勢研究",
        "code": "INM3513-009v1",
        "level": 3,
        "chunk_type": "task"
      }
    },
    {
      "id": "task_T2.1",
      "type": "工作任務",
      "content": "主要職責：T2AIoT系統需求分析與解決方案設計\n任務編號：T2.1\n任務名稱：客戶作業模式與流程分析\n職能級別：3\n工作產出：系統導入前後作業流程比較表、系統需求規劃書（含設備需求與系統功能清單）\n\n行為指標：\n- 系統導入前後之作業模式差異分析。\n- 辨識既有機/電/感測設備導入現況。\n- 能夠將新技術、產品、市場、AIoT標準規範等資訊，轉換為系統導入依據，並訂定出符合客戶需求的規格，或是制定全新的應用領域。\n\n所需知識（10項）：\n- 導入效益分析概念\n- 作業原理\n- 設備控制器與機構知識\n- 機電整合\n- 機器學習\n- AIoT發展趨勢\n- AIoT應用案例\n- 五力分析\n- 自動辨識與感測技術基礎知識（含感測器原理/趨勢）\n- 控制系統與機器聯網平台概念\n\n所需技能（6項）：\n- 作業流程問題分析能力\n- 流程最佳化\n- 跨部門溝通與協調能力\n- 需求規格書撰寫能力\n- 專案提案簡報及計畫書撰寫能力\n- 使用者操作介面設計能力",
      "metadata": {
        "task_id": "T2.1",
        "task_name": "客戶作業模式與流程分析",
        "main_responsibility": "T2AIoT系統需求分析與解決方案設計",
        "code": "INM3513-009v1",
        "level": 3,
        "chunk_type": "task"
      }
    },
    {
      "id": "task_T3.1",
      "type": "工作任務",
      "content": "主要職責：T3AIoT雲端與資料交換設計\n任務編號：T3.1\n任務名稱：AIoT雲端服務模式評估\n職能級別：4\n工作產出：雲端服務模式分析比較表、資訊安全風險評估報告\n\n行為指標：\n- 有效掌握客戶軟體系統開發與維護能力，協助客戶了解不同的雲端服務特性，選用較佳開發方案。\n- 評估各系統元件採用加密、簽章、去識別化的程度與時機。\n- 確保物聯網資料不易遭受竄改，及提供資料不可否認性確認功能。\n- 企業導入安全認證（如ISO 27001，Security+等）之評估。\n\n所需知識（7項）：\n- 導入效益分析概念\n- 雲端技術與服務架構基礎\n- Dev-Ops相關知識\n- 系統管理知識\n- 網路管理知識\n- AIoT資訊安全對策\n- 網路安全概論\n\n所需技能（5項）：\n- 雲端平台與中介軟體評估能力\n- 應用層系統架構與導入策略\n- 相關程式語言開發技能力\n- 營運衝擊分析能力\n- 資訊安全評估與導入策略",
      "metadata": {
        "task_id": "T3.1",
        "task_name": "AIoT雲端服務模式評估",
        "main_responsibility": "T3AIoT雲端與資料交換設計",
        "code": "INM3513-009v1",
        "level": 4,
        "chunk_type": "task"
      }
    },
    {
      "id": "task_T3.2",
      "type": "工作任務",
      "content": "主要職責：T3AIoT雲端與資料交換設計\n任務編號：T3.2\n任務名稱：規劃AIoT資料交換架構與標準\n職能級別：3\n工作產出：AIoT資料識別與編碼原則文件、AIoT資料交換格式報告\n\n行為指標：\n- 協助客戶了解系統或設備之框架基礎與編碼規範。\n- 制定AIoT各層級元件資料交換格式與通訊方式，並兼顧系統或設備間的整合需求。\n\n所需知識（10項）：\n- AIoT識別編碼架構基礎觀念\n- AIoT識別與資料服務架構元件\n- AIoT識別編碼設計原則與應用\n- 工業通訊標準\n- AIoT資訊安全對策\n- AIoT資料交換格式\n- 網路及資料庫概論\n- I/O通訊原理\n- 資料擷取、結構設計與儲存\n- 多感測訊號源融合與同步機制\n\n所需技能（6項）：\n- 應用層系統備援方案評估與導入策略\n- 服務/產品導入標準化識別編碼規範之能力\n- 資料格式設計能力\n- 跨系統資料交換技術應用能力\n- RE\n- 資訊可視化與預警技術應用",
      "metadata": {
        "task_id": "T3.2",
        "task_name": "規劃AIoT資料交換架構與標準",
        "main_responsibility": "T3AIoT雲端與資料交換設計",
        "code": "INM3513-009v1",
        "level": 3,
        "chunk_type": "task"
      }
    },
    {
      "id": "task_T4.1",
      "type": "工作任務",
      "content": "主要職責：T4AIoT通訊及感測系統建置與測試\n任務編號：T4.1\n任務名稱：AIoT通訊品質評估\n職能級別：3\n工作產出：通訊產品之讀取效能測試報告\n\n行為指標：\n- 針對通訊產品效能測試結果進行讀取效能分析並提出優化方案。\n- 協助客戶選擇適合之設備佈建場域，排除環境干擾因素影響使AIoT系統之讀取效能達最佳化。\n\n所需知識（6項）：\n- 工業通訊標準\n- 無線通訊技術\n- 天線設計基本原理\n- 基礎通訊原理\n- 電磁學知識\n- 信號調節技術\n\n所需技能（4項）：\n- 無線頻譜量測技術\n- 網路層系統備援方案評估與導入策略\n- 網路層無線通訊實作能力\n- 雜訊干擾防範處理",
      "metadata": {
        "task_id": "T4.1",
        "task_name": "AIoT通訊品質評估",
        "main_responsibility": "T4AIoT通訊及感測系統建置與測試",
        "code": "INM3513-009v1",
        "level": 3,
        "chunk_type": "task"
      }
    },
    {
      "id": "task_T5.1",
      "type": "工作任務",
      "content": "主要職責：T5AIoT系統更新與維護\n任務編號：T5.1\n任務名稱：AIoT功能新增與系統升級\n職能級別：4\n工作產出：新增功能規格書、系統導入與升級建置計畫書\n\n行為指標：\n- 能於既有系統架構中增加AIoT新功能。\n- 有效規劃AIoT系統導入與升級步驟，確保新舊系統能無縫接軌。\n- 評估與採用各式備援與高可靠性（HA）機制，定義系統服務層級協議（SLA）。\n\n所需知識（4項）：\n- 專案風險評估概念\n- 專案管理知識\n- 雲端備援與HA機制\n- 雲端彈性擴展知識\n\n所需技能（4項）：\n- 需求規格書撰寫能力\n- 專案提案簡報及計畫書撰寫能力\n- 系統備援方案評估與導入策略\n- 操作手冊撰寫能力",
      "metadata": {
        "task_id": "T5.1",
        "task_name": "AIoT功能新增與系統升級",
        "main_responsibility": "T5AIoT系統更新與維護",
        "code": "INM3513-009v1",
        "level": 4,
        "chunk_type": "task"
      }
    },
    {
      "id": "task_T6.1",
      "type": "工作任務",
      "content": "主要職責：T6機器聯網通訊與控制系統整合應用\n任務編號：T6.1\n任務名稱：分析與規劃機器聯網解決方案\n職能級別：4\n工作產出：設備清冊與現況評估報告、機器聯網通訊架構與整合建議書\n\n行為指標：\n- 能辨識並盤點現場控制器、感測器、I/O模組等設備資源，釐清其介面與資料交換方式。\n- 瞭解公司機器聯網策略、現況與資源投入程度，規劃AIoT導入順序與方案，並制定與選用合適的通訊協定與標準。\n\n所需知識（6項）：\n- 設備控制器與機構知識\n- 控制系統與機器聯網平台概念\n- 工業通訊標準\n- 機電整合\n- 自動辨識與感測技術基礎知識（含感測器原理/趨勢）\n- 通訊管理技術\n\n所需技能（7項）：\n- 跨系統資料交換技術應用能力\n- 感知層感測器規格分析能力\n- 資料搜集與分析能力\n- 跨部門溝通與協調能力\n- 需求規格書撰寫能力\n- 通訊與設備技術應用能力\n- 機器聯網應用技術",
      "metadata": {
        "task_id": "T6.1",
        "task_name": "分析與規劃機器聯網解決方案",
        "main_responsibility": "T6機器聯網通訊與控制系統整合應用",
        "code": "INM3513-009v1",
        "level": 4,
        "chunk_type": "task"
      }
    },
    {
      "id": "task_T6.2",
      "type": "工作任務",
      "content": "主要職責：T6機器聯網通訊與控制系統整合應用\n任務編號：T6.2\n任務名稱：識別數據與制定擷取、傳輸儲存與安全管理方式\n職能級別：4\n工作產出：資料識別與擷取規劃書、資料安全傳輸與儲存規劃方案\n\n行為指標：\n- 評估機器資料擷取自動化可行方案，制定擷取方式、頻率與結構化欄位。\n- 制定資料擷取所使用的通訊與傳輸方式，規劃全程安全管理機制，包含擷取不落地、傳輸加密、安全儲存機制、資料調用安全稽核方式。\n\n所需知識（13項）：\n- 工業通訊標準\n- 設備控制器與機構知識\n- 自動辨識與感測技術基礎知識（含感測器原理/趨勢）\n- AIoT識別與資料服務架構元件\n- AIoT資料交換格式\n- I/O通訊原理\n- 資料擷取、結構設計與儲存\n- 多感測訊號源融合與同步機制\n- AIoT資訊安全對策\n- 網路及資料庫概論\n- 通訊管理技術\n- 雲端與平台架構應用\n- ICS/SCADA安全概論\n\n所需技能（7項）：\n- 相關程式語言開發技能力\n- 資料格式設計能力\n- 通訊與設備技術應用能力\n- 感知層感測器規格分析能力\n- 機器聯網應用技術\n- 資訊安全評估與導入策略\n- 工控系統安全設計能力",
      "metadata": {
        "task_id": "T6.2",
        "task_name": "識別數據與制定擷取、傳輸儲存與安全管理方式",
        "main_responsibility": "T6機器聯網通訊與控制系統整合應用",
        "code": "INM3513-009v1",
        "level": 4,
        "chunk_type": "task"
      }
    },
    {
      "id": "task_T6.3",
      "type": "工作任務",
      "content": "主要職責：T6機器聯網通訊與控制系統整合應用\n任務編號：T6.3\n任務名稱：建置機器聯網感測、通訊與應用\n職能級別：5\n工作產出：整合與建置機電聯網感測與傳輸機制、多系統資料共享應用與視覺化設計文件、建置與擴大機器聯網應用\n\n行為指標：\n- 能整合異質設備與資料來源，設計跨系統通訊與資料接軌方案。\n- 能建構應用層儀表板或資料展示介面，支援資料即時監控、預警或生產效率分析。\n- 依據企業聯網策略與導入規劃，建置多元機器聯網應用機制，並逐步擴大應用範圍，達成預防問題發生、提升人機稼動、產能最佳化等目的。同時制定方案維運計劃，提出完整的系統失效分析與故障排除對策。\n\n所需知識（13項）：\n- 機電整合\n- I/O通訊原理\n- 資料擷取、結構設計與儲存\n- 多感測訊號源融合與同步機制\n- 信號調節技術\n- 通訊管理技術\n- 軟體應用與開源技術\n- 人機界面\n- 專案管理知識\n- Dev-Ops相關知識\n- 系統管理知識\n- 網路管理知識\n- 雲端備援與HA機制\n\n所需技能（14項）：\n- 相關程式語言開發技能力\n- 跨系統資料交換技術應用能力\n- 雜訊干擾防範處理\n- 感知層感測器規格分析能力\n- 信號濾波\n- 機器聯網應用技術\n- 資訊可視化與預警技術應用\n- 測試程序與工具\n- 撰寫測試報告能力\n- 系統備援方案評估與導入策略\n- 作業流程問題分析能力\n- 跨部門溝通與協調能力\n- 網路層系統備援方案評估與導入策略\n- 問題排除與系統維護規劃能力",
      "metadata": {
        "task_id": "T6.3",
        "task_name": "建置機器聯網感測、通訊與應用",
        "main_responsibility": "T6機器聯網通訊與控制系統整合應用",
        "code": "INM3513-009v1",
        "level": 5,
        "chunk_type": "task"
      }
    },
    {
      "id": "task_T6.4",
      "type": "工作任務",
      "content": "主要職責：T6機器聯網通訊與控制系統整合應用\n任務編號：T6.4\n任務名稱：落實工控資安\n職能級別：5\n工作產出：產出工控資安風險管理規劃、導入與落實工控資安標準與防護機制\n\n行為指標：\n- 識別工控資安風險，評估工控資安成熟度。規劃機器與感測數據之安全使用管理辦法，包含認證、授權、通訊加密與稽核方式。\n- 完成工控資安檢測與監控，達成工控資安標準及規範，例如IEC62443、IEC TR63283-3:2022、Machinery。\n\n所需知識（8項）：\n- 專案風險評估概念\n- Dev-Ops相關知識\n- AIoT資訊安全對策\n- 網路安全概論\n- ICS/SCADA安全概論\n- AIoT相關國際標準\n- 工業通訊標準\n- 人機界面\n\n所需技能（7項）：\n- 資料搜集與分析能力\n- 資訊安全評估與導入策略\n- 操作手冊撰寫能力\n- 工控系統安全設計能力\n- 跨部門溝通與協調能力\n- 資訊可視化與預警技術應用\n- 機器聯網應用技術",
      "metadata": {
        "task_id": "T6.4",
        "task_name": "落實工控資安",
        "main_responsibility": "T6機器聯網通訊與控制系統整合應用",
        "code": "INM3513-009v1",
        "level": 5,
        "chunk_type": "task"
      }
    },
    {
      "id": "knowledge_skills_1",
      "type": "知識技能",
      "content": "職責領域：T1AIoT標準與應用趨勢研究\n\n需具備知識（4項）：\n- K01: AIoT系統基本架構\n- K02: AIoT相關國際標準\n- K03: 基礎通訊原理\n- K04: 工業通訊標準\n\n需具備技能（3項）：\n- S01: 資料搜集與分析能力\n- S02: 英文閱讀能力\n- S03: 瞭解判讀產品規格書能力",
      "metadata": {
        "main_responsibility": "T1AIoT標準與應用趨勢研究",
        "code": "INM3513-009v1",
        "chunk_type": "knowledge_skills"
      }
    },
    {
      "id": "knowledge_skills_2",
      "type": "知識技能",
      "content": "職責領域：T2AIoT系統需求分析與解決方案設計\n\n需具備知識（10項）：\n- K05: AIoT發展趨勢\n- K06: AIoT應用案例\n- K07: 導入效益分析概念\n- K08: 作業原理\n- K09: 設備控制器與機構知識\n- K10: 機電整合\n- K11: 機器學習\n- K12: 五力分析\n- K13: 自動辨識與感測技術基礎知識（含感測器原理/趨勢）\n- K14: 控制系統與機器聯網平台概念\n\n需具備技能（6項）：\n- S07: 作業流程問題分析能力\n- S08: 流程最佳化\n- S09: 跨部門溝通與協調能力\n- S10: 需求規格書撰寫能力\n- S11: 專案提案簡報及計畫書撰寫能力\n- S12: 使用者操作介面設計能力",
      "metadata": {
        "main_responsibility": "T2AIoT系統需求分析與解決方案設計",
        "code": "INM3513-009v1",
        "chunk_type": "knowledge_skills"
      }
    },
    {
      "id": "knowledge_skills_3",
      "type": "知識技能",
      "content": "職責領域：T3AIoT雲端與資料交換設計\n\n需具備知識（16項）：\n- K04: 工業通訊標準\n- K07: 導入效益分析概念\n- K17: 雲端技術與服務架構基礎\n- K18: Dev-Ops相關知識\n- K19: 系統管理知識\n- K20: 網路管理知識\n- K21: AIoT資訊安全對策\n- K22: 網路安全概論\n- K23: AIoT識別編碼架構基礎觀念\n- K24: AIoT識別與資料服務架構元件\n- K25: AIoT識別編碼設計原則與應用\n- K26: AIoT資料交換格式\n- K27: 網路及資料庫概論\n- K28: I/O通訊原理\n- K29: 資料擷取、結構設計與儲存\n- K30: 多感測訊號源融合與同步機制\n\n需具備技能（11項）：\n- S15: 營運衝擊分析能力\n- S16: 雲端平台與中介軟體評估能力\n- S17: 應用層系統架構與導入策略\n- S18: 相關程式語言開發技能力\n- S19: 資訊安全評估與導入策略\n- S20: 應用層系統備援方案評估與導入策略\n- S21: 服務/產品導入標準化識別編碼規範之能力\n- S22: 資料格式設計能力\n- S23: 跨系統資料交換技術應用能力\n- S24: RE\n- S25: 資訊可視化與預警技術應用",
      "metadata": {
        "main_responsibility": "T3AIoT雲端與資料交換設計",
        "code": "INM3513-009v1",
        "chunk_type": "knowledge_skills"
      }
    },
    {
      "id": "knowledge_skills_4",
      "type": "知識技能",
      "content": "職責領域：T4AIoT通訊及感測系統建置與測試\n\n需具備知識（6項）：\n- K03: 基礎通訊原理\n- K04: 工業通訊標準\n- K32: 無線通訊技術\n- K33: 天線設計基本原理\n- K34: 電磁學知識\n- K35: 信號調節技術\n\n需具備技能（4項）：\n- S29: 無線頻譜量測技術\n- S30: 網路層系統備援方案評估與導入策略\n- S31: 網路層無線通訊實作能力\n- S32: 雜訊干擾防範處理",
      "metadata": {
        "main_responsibility": "T4AIoT通訊及感測系統建置與測試",
        "code": "INM3513-009v1",
        "chunk_type": "knowledge_skills"
      }
    },
    {
      "id": "knowledge_skills_5",
      "type": "知識技能",
      "content": "職責領域：T5AIoT系統更新與維護\n\n需具備知識（4項）：\n- K15: 專案風險評估概念\n- K16: 專案管理知識\n- K38: 雲端備援與HA機制\n- K39: 雲端彈性擴展知識\n\n需具備技能（4項）：\n- S10: 需求規格書撰寫能力\n- S11: 專案提案簡報及計畫書撰寫能力\n- S28: 系統備援方案評估與導入策略\n- S37: 操作手冊撰寫能力",
      "metadata": {
        "main_responsibility": "T5AIoT系統更新與維護",
        "code": "INM3513-009v1",
        "chunk_type": "knowledge_skills"
      }
    },
    {
      "id": "knowledge_skills_6",
      "type": "知識技能",
      "content": "職責領域：T6機器聯網通訊與控制系統整合應用\n\n需具備知識（26項）：\n- K02: AIoT相關國際標準\n- K04: 工業通訊標準\n- K09: 設備控制器與機構知識\n- K10: 機電整合\n- K13: 自動辨識與感測技術基礎知識（含感測器原理/趨勢）\n- K14: 控制系統與機器聯網平台概念\n- K15: 專案風險評估概念\n- K16: 專案管理知識\n- K18: Dev-Ops相關知識\n- K19: 系統管理知識\n- K20: 網路管理知識\n- K21: AIoT資訊安全對策\n- K22: 網路安全概論\n- K24: AIoT識別與資料服務架構元件\n- K26: AIoT資料交換格式\n- K27: 網路及資料庫概論\n- K28: I/O通訊原理\n- K29: 資料擷取、結構設計與儲存\n- K30: 多感測訊號源融合與同步機制\n- K35: 信號調節技術\n- K38: 雲端備援與HA機制\n- K41: 通訊管理技術\n- K42: 雲端與平台架構應用\n- K43: ICS/SCADA安全概論\n- K44: 軟體應用與開源技術\n- K45: 人機界面\n\n需具備技能（21項）：\n- S01: 資料搜集與分析能力\n- S07: 作業流程問題分析能力\n- S09: 跨部門溝通與協調能力\n- S10: 需求規格書撰寫能力\n- S18: 相關程式語言開發技能力\n- S19: 資訊安全評估與導入策略\n- S22: 資料格式設計能力\n- S23: 跨系統資料交換技術應用能力\n- S25: 資訊可視化與預警技術應用\n- S26: 測試程序與工具\n- S27: 撰寫測試報告能力\n- S28: 系統備援方案評估與導入策略\n- S30: 網路層系統備援方案評估與導入策略\n- S32: 雜訊干擾防範處理\n- S33: 感知層感測器規格分析能力\n- S35: 信號濾波\n- S37: 操作手冊撰寫能力\n- S38: 問題排除與系統維護規劃能力\n- S39: 通訊與設備技術應用能力\n- S40: 機器聯網應用技術\n- S41: 工控系統安全設計能力",
      "metadata": {
        "main_responsibility": "T6機器聯網通訊與控制系統整合應用",
        "code": "INM3513-009v1",
        "chunk_type": "knowledge_skills"
      }
    },
    {
      "id": "summary",
      "type": "完整摘要",
      "content": "【AIoT標準與應用趨職能基準摘要】\n\n一、基本資訊\n- 職能代碼：INM3513-009v1\n- 職類別：製造 / 生產管理資訊科技／網路規劃與建置管理資訊科技 / 軟體開發及程式設計科學、技術、工程、數學/工程及技術\n- 職業別：科學及工程專業人員機械工程師電子工程師其他軟體、應用程式開發人員及分析師資料庫及網路專業人員電腦網路專業人員電腦網路及系統技術員\n- 基準級別：4\n\n二、工作描述\n依據產業應用需求，具備運用AIoT系統整合與應用能力，並且熟悉感測模組、通訊技術、邊緣設備與雲端平台之部署與串接。能依場域特性規劃適配的資料傳輸架構以整合必要的多通訊協定，實作資料擷取、格式轉換與視覺化呈現，並具備資訊安全意識與系統維運能力，協助場域導入、分析、善用感測數據達成數位化與智慧化應用目標。\n\n三、主要職責與任務（10項）\n- T1.1 蒐集國際及國內AIoT相關標準\n- T2.1 客戶作業模式與流程分析\n- T3.1 AIoT雲端服務模式評估\n- T3.2 規劃AIoT資料交換架構與標準\n- T4.1 AIoT通訊品質評估\n- T5.1 AIoT功能新增與系統升級\n- T6.1 分析與規劃機器聯網解決方案\n- T6.2 識別數據與制定擷取、傳輸儲存與安全管理方式\n- T6.3 建置機器聯網感測、通訊與應用\n- T6.4 落實工控資安\n\n四、職能要求\n- 知識項目：45項\n- 技能項目：41項\n- 態度項目：0項\n\n五、建議條件\n",
      "metadata": {
        "code": "INM3513-009v1",
        "name": "AIoT標準與應用趨",
        "chunk_type": "summary"
      }
    }
  ],
  "parse_success": true,
  "parse_errors": []
}