{
  "metadata": {
    "code": "BHR2422-001v4",
    "name": "職能分析人員",
    "update_date": "2024/12/15",
    "version": "V4",
    "status": "最新版本",
    "source_file": "C:\\Users\\User\\Graph_RAG_test\\data\\raw_pdf\\職能分析人員-職能基準.pdf"
  },
  "basic_info": {
    "category": "企業經營管理／人力資源管理",
    "category_code": "BHR",
    "occupation": "人事及員工培訓專業人員",
    "occupation_code": "2422",
    "industry": [
      "教育服務業／教育服務業"
    ],
    "industry_code": [
      "P8574"
    ],
    "job_description": "依據產業或組織發展需求，蒐集盤點相關職業／職務資料，並分析及驗證工作任務所需知識、技能與態度之完整性及正確性，並規劃未來的應用方式及預期效益。",
    "level": 4,
    "requirements": ""
  },
  "competency_tasks": [
    {
      "main_responsibility": "T1職能需求項目分析",
      "task_id": "T1.1",
      "task_name": "分析產業或組織職能需",
      "output": "產業或組織職能需求分析文件、職業／職務清單、標的項目及應用效益說明文件",
      "behaviors": [
        "依產業趨勢／機構需求與專家意見確認職業／職務範疇。",
        "設定篩選條件，選定發展標的之關鍵職業／職務項目。",
        "蒐集完整關鍵職業／職務文獻資料，確認該職業／職務之從業人員的工作範疇。",
        "依關鍵職業／職務項目規劃未來的應用方式及預期效益。"
      ],
      "knowledge": [
        "K01",
        "K02",
        "K03",
        "K04",
        "K05"
      ],
      "skills": [
        "S01",
        "S02",
        "S03",
        "S04"
      ],
      "level": 3
    },
    {
      "main_responsibility": "T2分析職業／職務職能",
      "task_id": "T2.1",
      "task_name": "分析工作任務及職能內涵",
      "output": "職業／職務名稱與工作描述、行為指標",
      "behaviors": [
        "依據選定之方法，分析工作任務，並確認工作內容的完整性與正確性。",
        "確保工作任務分析內容，符合職業要求。",
        "確保行為指標能明確反應行為表現及能力水準。",
        "分析工作任務所需具備之知識、技能與態度，以符合實務工作及發展趨勢。"
      ],
      "knowledge": [
        "K07",
        "K08",
        "K09"
      ],
      "skills": [
        "S06",
        "S07",
        "S08"
      ],
      "level": 4
    },
    {
      "main_responsibility": "T3驗證及完成職能模型",
      "task_id": "T3.1",
      "task_name": "實施驗證",
      "output": "職能驗證工具、驗證結果報告",
      "behaviors": [
        "依據所選擇的方法，設計驗證對應工具。",
        "依據建置標的屬性與方法，邀請具代表性專家或驗證對象參與驗證，確保職能模型內容的正確性與重要度。"
      ],
      "knowledge": [
        "K08",
        "K10",
        "K11"
      ],
      "skills": [
        "S02",
        "S04",
        "S07",
        "S09"
      ],
      "level": 4
    },
    {
      "main_responsibility": "T3驗證及完成職能模型",
      "task_id": "T3.2",
      "task_name": "修正及完成職能模型",
      "output": "職能模型",
      "behaviors": [
        "依據驗證結果修正職能模型並請專家確認，以符合產業或組織需求。"
      ],
      "knowledge": [
        "K08"
      ],
      "skills": [
        "S02",
        "S04",
        "S08"
      ],
      "level": 4
    }
  ],
  "competency_knowledge": [
    {
      "code": "K01",
      "name": "勞動政策發展及趨勢",
      "category": "知識"
    },
    {
      "code": "K02",
      "name": "產業發展政策及趨勢",
      "category": "知識"
    },
    {
      "code": "K03",
      "name": "行業與職業分類",
      "category": "知識"
    },
    {
      "code": "K04",
      "name": "職能導向人力資源管理",
      "category": "知識"
    },
    {
      "code": "K05",
      "name": "職能應用概念",
      "category": "知識"
    },
    {
      "code": "K06",
      "name": "職能分析方法",
      "category": "知識"
    },
    {
      "code": "K07",
      "name": "工作分析",
      "category": "知識"
    },
    {
      "code": "K08",
      "name": "職能分析方法及流程",
      "category": "知識"
    },
    {
      "code": "K09",
      "name": "職能編撰原則",
      "category": "知識"
    },
    {
      "code": "K10",
      "name": "量化研究方法概念",
      "category": "知識"
    },
    {
      "code": "K11",
      "name": "質性研究方法概念",
      "category": "知識"
    }
  ],
  "competency_skills": [
    {
      "code": "S01",
      "name": "資料蒐集能力",
      "category": "技能"
    },
    {
      "code": "S02",
      "name": "資料分析與解讀能力",
      "category": "技能"
    },
    {
      "code": "S03",
      "name": "判斷與思考能力",
      "category": "技能"
    },
    {
      "code": "S04",
      "name": "問題分析與解決能力",
      "category": "技能"
    },
    {
      "code": "S05",
      "name": "職能發展工具應用能力",
      "category": "技能"
    },
    {
      "code": "S06",
      "name": "工作分析能力",
      "category": "技能"
    },
    {
      "code": "S07",
      "name": "訪談技巧",
      "category": "技能"
    },
    {
      "code": "S08",
      "name": "文書撰寫能力",
      "category": "技能"
    },
    {
      "code": "S09",
      "name": "問卷設計與統計分析能力",
      "category": "技能"
    }
  ],
  "competency_attitudes": [
    {
      "code": "A01",
      "name": "主動積極",
      "description": "不需他人指示或要求能自動自發做事，面臨問題立即採取行動加以解決，且為達目標願意主動承擔額外責任。",
      "category": "態度"
    },
    {
      "code": "A02",
      "name": "謹慎細心",
      "description": "對於任務的執行過程，能謹慎考量及處理所有細節，精確地檢視每個程序，並持續對其保持高度關注。",
      "category": "態度"
    },
    {
      "code": "A03",
      "name": "壓力容忍",
      "description": "冷靜且有效地應對及處理高度緊張的情況或壓力，如緊迫的時間、不友善的人、各類突發事件及危急狀況，並能以適當的方式紓解自身壓力。",
      "category": "態度"
    },
    {
      "code": "A04",
      "name": "應對不確定性",
      "description": "當狀況不明或問題不夠具體的情況下，能在必要時採取行動，以有效釐清模糊不清的態勢。",
      "category": "態度"
    },
    {
      "code": "A05",
      "name": "自我管理",
      "description": "設立定義明確且實際可行的個人目標；對於及時完成任務展現高度進取、努力、承諾及負責任的行為。",
      "category": "態度"
    }
  ],
  "chunks_for_rag": [
    {
      "id": "basic_info",
      "type": "基本資訊",
      "content": "職能基準：職能需求項目分析\n代碼：BHR2422-001v4\n版本：V4\n職類別：企業經營管理／人力資源管理（代碼：BHR）\n職業別：人事及員工培訓專業人員（代碼：2422）\n行業別：教育服務業／教育服務業（代碼：P8574）\n基準級別：4\n工作描述：依據產業或組織發展需求，蒐集盤點相關職業／職務資料，並分析及驗證工作任務所需知識、技能與態度之完整性及正確性，並規劃未來的應用方式及預期效益。\n建議條件：\n更新日期：2024/12/15",
      "metadata": {
        "code": "BHR2422-001v4",
        "name": "職能需求項目分析",
        "level": 4,
        "chunk_type": "overview"
      }
    },
    {
      "id": "task_T1.1",
      "type": "工作任務",
      "content": "主要職責：T1職能需求項目分析\n任務編號：T1.1\n任務名稱：分析產業或組織職能需\n職能級別：3\n工作產出：產業或組織職能需求分析文件、職業／職務清單、標的項目及應用效益說明文件\n\n行為指標：\n- 依產業趨勢／機構需求與專家意見確認職業／職務範疇。\n- 設定篩選條件，選定發展標的之關鍵職業／職務項目。\n- 蒐集完整關鍵職業／職務文獻資料，確認該職業／職務之從業人員的工作範疇。\n- 依關鍵職業／職務項目規劃未來的應用方式及預期效益。\n\n所需知識（5項）：\n- 勞動政策發展及趨勢\n- 產業發展政策及趨勢\n- 行業與職業分類\n- 職能導向人力資源管理\n- 職能應用概念\n\n所需技能（4項）：\n- 資料蒐集能力\n- 資料分析與解讀能力\n- 判斷與思考能力\n- 問題分析與解決能力",
      "metadata": {
        "task_id": "T1.1",
        "task_name": "分析產業或組織職能需",
        "main_responsibility": "T1職能需求項目分析",
        "code": "BHR2422-001v4",
        "level": 3,
        "chunk_type": "task"
      }
    },
    {
      "id": "task_T2.1",
      "type": "工作任務",
      "content": "主要職責：T2分析職業／職務職能\n任務編號：T2.1\n任務名稱：分析工作任務及職能內涵\n職能級別：4\n工作產出：職業／職務名稱與工作描述、行為指標\n\n行為指標：\n- 依據選定之方法，分析工作任務，並確認工作內容的完整性與正確性。\n- 確保工作任務分析內容，符合職業要求。\n- 確保行為指標能明確反應行為表現及能力水準。\n- 分析工作任務所需具備之知識、技能與態度，以符合實務工作及發展趨勢。\n\n所需知識（3項）：\n- 工作分析\n- 職能分析方法及流程\n- 職能編撰原則\n\n所需技能（3項）：\n- 工作分析能力\n- 訪談技巧\n- 文書撰寫能力",
      "metadata": {
        "task_id": "T2.1",
        "task_name": "分析工作任務及職能內涵",
        "main_responsibility": "T2分析職業／職務職能",
        "code": "BHR2422-001v4",
        "level": 4,
        "chunk_type": "task"
      }
    },
    {
      "id": "task_T3.1",
      "type": "工作任務",
      "content": "主要職責：T3驗證及完成職能模型\n任務編號：T3.1\n任務名稱：實施驗證\n職能級別：4\n工作產出：職能驗證工具、驗證結果報告\n\n行為指標：\n- 依據所選擇的方法，設計驗證對應工具。\n- 依據建置標的屬性與方法，邀請具代表性專家或驗證對象參與驗證，確保職能模型內容的正確性與重要度。\n\n所需知識（3項）：\n- 職能分析方法及流程\n- 量化研究方法概念\n- 質性研究方法概念\n\n所需技能（4項）：\n- 資料分析與解讀能力\n- 問題分析與解決能力\n- 訪談技巧\n- 問卷設計與統計分析能力",
      "metadata": {
        "task_id": "T3.1",
        "task_name": "實施驗證",
        "main_responsibility": "T3驗證及完成職能模型",
        "code": "BHR2422-001v4",
        "level": 4,
        "chunk_type": "task"
      }
    },
    {
      "id": "task_T3.2",
      "type": "工作任務",
      "content": "主要職責：T3驗證及完成職能模型\n任務編號：T3.2\n任務名稱：修正及完成職能模型\n職能級別：4\n工作產出：職能模型\n\n行為指標：\n- 依據驗證結果修正職能模型並請專家確認，以符合產業或組織需求。\n\n所需知識（1項）：\n- 職能分析方法及流程\n\n所需技能（3項）：\n- 資料分析與解讀能力\n- 問題分析與解決能力\n- 文書撰寫能力",
      "metadata": {
        "task_id": "T3.2",
        "task_name": "修正及完成職能模型",
        "main_responsibility": "T3驗證及完成職能模型",
        "code": "BHR2422-001v4",
        "level": 4,
        "chunk_type": "task"
      }
    },
    {
      "id": "knowledge_skills_1",
      "type": "知識技能",
      "content": "職責領域：T1職能需求項目分析\n\n需具備知識（5項）：\n- K01: 勞動政策發展及趨勢\n- K02: 產業發展政策及趨勢\n- K03: 行業與職業分類\n- K04: 職能導向人力資源管理\n- K05: 職能應用概念\n\n需具備技能（4項）：\n- S01: 資料蒐集能力\n- S02: 資料分析與解讀能力\n- S03: 判斷與思考能力\n- S04: 問題分析與解決能力",
      "metadata": {
        "main_responsibility": "T1職能需求項目分析",
        "code": "BHR2422-001v4",
        "chunk_type": "knowledge_skills"
      }
    },
    {
      "id": "knowledge_skills_2",
      "type": "知識技能",
      "content": "職責領域：T2分析職業／職務職能\n\n需具備知識（3項）：\n- K07: 工作分析\n- K08: 職能分析方法及流程\n- K09: 職能編撰原則\n\n需具備技能（3項）：\n- S06: 工作分析能力\n- S07: 訪談技巧\n- S08: 文書撰寫能力",
      "metadata": {
        "main_responsibility": "T2分析職業／職務職能",
        "code": "BHR2422-001v4",
        "chunk_type": "knowledge_skills"
      }
    },
    {
      "id": "knowledge_skills_3",
      "type": "知識技能",
      "content": "職責領域：T3驗證及完成職能模型\n\n需具備知識（3項）：\n- K08: 職能分析方法及流程\n- K10: 量化研究方法概念\n- K11: 質性研究方法概念\n\n需具備技能（5項）：\n- S02: 資料分析與解讀能力\n- S04: 問題分析與解決能力\n- S07: 訪談技巧\n- S08: 文書撰寫能力\n- S09: 問卷設計與統計分析能力",
      "metadata": {
        "main_responsibility": "T3驗證及完成職能模型",
        "code": "BHR2422-001v4",
        "chunk_type": "knowledge_skills"
      }
    },
    {
      "id": "attitudes",
      "type": "職能態度",
      "content": "職能態度要求（5項）：\n\nA01 - 主動積極：不需他人指示或要求能自動自發做事，面臨問題立即採取行動加以解決，且為達目標願意主動承擔額外責任。\n\nA02 - 謹慎細心：對於任務的執行過程，能謹慎考量及處理所有細節，精確地檢視每個程序，並持續對其保持高度關注。\n\nA03 - 壓力容忍：冷靜且有效地應對及處理高度緊張的情況或壓力，如緊迫的時間、不友善的人、各類突發事件及危急狀況，並能以適當的方式紓解自身壓力。\n\nA04 - 應對不確定性：當狀況不明或問題不夠具體的情況下，能在必要時採取行動，以有效釐清模糊不清的態勢。\n\nA05 - 自我管理：設立定義明確且實際可行的個人目標；對於及時完成任務展現高度進取、努力、承諾及負責任的行為。",
      "metadata": {
        "code": "BHR2422-001v4",
        "count": 5,
        "chunk_type": "attitudes"
      }
    },
    {
      "id": "summary",
      "type": "完整摘要",
      "content": "【職能需求項目分析職能基準摘要】\n\n一、基本資訊\n- 職能代碼：BHR2422-001v4\n- 職類別：企業經營管理／人力資源管理\n- 職業別：人事及員工培訓專業人員\n- 基準級別：4\n\n二、工作描述\n依據產業或組織發展需求，蒐集盤點相關職業／職務資料，並分析及驗證工作任務所需知識、技能與態度之完整性及正確性，並規劃未來的應用方式及預期效益。\n\n三、主要職責與任務（4項）\n- T1.1 分析產業或組織職能需\n- T2.1 分析工作任務及職能內涵\n- T3.1 實施驗證\n- T3.2 修正及完成職能模型\n\n四、職能要求\n- 知識項目：11項\n- 技能項目：9項\n- 態度項目：5項\n\n五、建議條件\n",
      "metadata": {
        "code": "BHR2422-001v4",
        "name": "職能需求項目分析",
        "chunk_type": "summary"
      }
    }
  ],
  "parse_success": true,
  "parse_errors": []
}