{
  "metadata": {
    "code": "MPM8122-005v2",
    "name": "陽極處理設備操作人員",
    "update_date": "2024/12/15",
    "version": "V2",
    "status": "最新版本",
    "source_file": "C:\\Users\\User\\Graph_RAG_test\\data\\raw_pdf\\陽極處理設備操作人員-職能基準.pdf"
  },
  "basic_info": {
    "category": "製造／生產管理",
    "category_code": "MPM",
    "occupation": "金屬表面處理機械操作人員",
    "occupation_code": "8122",
    "industry": [
      "製造業／金屬手工具及模具製造業"
    ],
    "industry_code": [
      "C2512"
    ],
    "job_description": "從事陽極處理設備操作、維護及保養等工作。",
    "level": 3,
    "requirements": ""
  },
  "competency_tasks": [
    {
      "main_responsibility": "T1陽極處理生產設備整備作業",
      "task_id": "T1.1",
      "task_name": "設備啟動與清潔作業",
      "output": "機台保養紀錄表",
      "behaviors": [
        "檢查陽極處理設備之動態機構行程是否有障礙物或不順暢。",
        "依正確的操作程序啟動設備電源開關。",
        "執行陽極處理設備清潔保養作業。"
      ],
      "knowledge": [
        "K01",
        "K02",
        "K03"
      ],
      "skills": [
        "S01",
        "S02",
        "S03",
        "S04"
      ],
      "level": 3
    },
    {
      "main_responsibility": "T1陽極處理生產設備整備作業",
      "task_id": "T1.2",
      "task_name": "執行安全檢查作業",
      "output": null,
      "behaviors": [
        "瞭解製程產生的有害物質對人體造成的影響，並能做好適切的防護措施。",
        "執行陽極處理設備安全檢查及防護作業。",
        "製程中隨時監看設備運作，並掌握製程狀態與工作安全。"
      ],
      "knowledge": [
        "K04",
        "K05",
        "K06"
      ],
      "skills": [
        "S01",
        "S03",
        "S05"
      ],
      "level": 3
    },
    {
      "main_responsibility": "T2陽極處理產線設備操作",
      "task_id": "T2.1",
      "task_name": "熟練機台操作",
      "output": null,
      "behaviors": [
        "熟練機台的操作。",
        "熟練操作人機介面的參數設定與調整",
        "依製令之製程規範落實執行與管控。"
      ],
      "knowledge": [
        "K01",
        "K12",
        "K13",
        "K14"
      ],
      "skills": [
        "S02",
        "S05",
        "S09",
        "S10"
      ],
      "level": 3
    },
    {
      "main_responsibility": "T2陽極處理產線設備操作",
      "task_id": "T2.2",
      "task_name": "製程參數設定",
      "output": null,
      "behaviors": [
        "依製造程序書及製程參數表使用正確的製程處理液、添加劑，以正確掌握陽極處理操作時的成分和濃度。",
        "依製令要求或成品規格設定時間、元素、溫度、濃度之相關參數設定。"
      ],
      "knowledge": [
        "K09",
        "K10",
        "K13",
        "K15"
      ],
      "skills": [
        "S08",
        "S10"
      ],
      "level": 3
    },
    {
      "main_responsibility": "T3小量生產作業與檢測",
      "task_id": "T3.1",
      "task_name": "小量上料",
      "output": null,
      "behaviors": [
        "小量材料上架並檢查料件吊掛位置是否合宜。",
        "確認料件吊架是否合適，並檢查料件夾持是否穩固。"
      ],
      "knowledge": [
        "K11",
        "K12"
      ],
      "skills": [
        "S09"
      ],
      "level": 3
    },
    {
      "main_responsibility": "T4量產操作與保養維護",
      "task_id": "T4.1",
      "task_name": "批量生產作業",
      "output": "成品",
      "behaviors": [
        "依樣品檢測後的優化參數進行設定，並注意設備在製程中的變異及調整。",
        "監看成品料件的特徵變異。",
        "定時進行成品料件的取樣與尺寸量測。",
        "執行設備的故障通報。",
        "配合品保部門成品檢測取樣作業。",
        "執行設備保養作業。"
      ],
      "knowledge": [
        "K08",
        "K11",
        "K12",
        "K17",
        "K18"
      ],
      "skills": [
        "S04",
        "S07",
        "S09",
        "S10",
        "S11"
      ],
      "level": 3
    },
    {
      "main_responsibility": "T4量產操作與保養維護",
      "task_id": "T4.2",
      "task_name": "廢棄物處理與保養維護",
      "output": null,
      "behaviors": [
        "依廠內廢棄物及廢液處理注意事項執行廢棄物及廢液的保存及處理。",
        "執行生產時每日保養作業及定期保養維護之操作。"
      ],
      "knowledge": [
        "K02",
        "K19",
        "K20"
      ],
      "skills": [
        "S02",
        "S03",
        "S12"
      ],
      "level": 3
    }
  ],
  "competency_knowledge": [
    {
      "code": "K01",
      "name": "陽極處理機台設備的運作原理、規格",
      "category": "知識"
    },
    {
      "code": "K02",
      "name": "陽極處理設備清潔與保養注意事項",
      "category": "知識"
    },
    {
      "code": "K03",
      "name": "標準作業程序",
      "category": "知識"
    },
    {
      "code": "K04",
      "name": "安全設施認知與作業程序規範",
      "category": "知識"
    },
    {
      "code": "K05",
      "name": "陽極處理機台設備操作安全",
      "category": "知識"
    },
    {
      "code": "K06",
      "name": "職業安全與衛生相關規範",
      "category": "知識"
    },
    {
      "code": "K07",
      "name": "料件的清潔作業",
      "category": "知識"
    },
    {
      "code": "K08",
      "name": "量測與檢驗規範",
      "category": "知識"
    },
    {
      "code": "K09",
      "name": "陽極處理液與前處理液的功能與特性",
      "category": "知識"
    },
    {
      "code": "K10",
      "name": "添加劑的功能與特性",
      "category": "知識"
    },
    {
      "code": "K11",
      "name": "夾(治)具概論",
      "category": "知識"
    },
    {
      "code": "K12",
      "name": "料件吊掛注意事項",
      "category": "知識"
    },
    {
      "code": "K13",
      "name": "人機介面的功能參數規範",
      "category": "知識"
    },
    {
      "code": "K14",
      "name": "品質管理概論",
      "category": "知識"
    },
    {
      "code": "K15",
      "name": "電化學反應概論",
      "category": "知識"
    },
    {
      "code": "K16",
      "name": "製程參數的內涵",
      "category": "知識"
    },
    {
      "code": "K17",
      "name": "料件表面處理後的特徵變異",
      "category": "知識"
    },
    {
      "code": "K18",
      "name": "設備運作變異及調整注意事項",
      "category": "知識"
    },
    {
      "code": "K19",
      "name": "環保法規相關規範",
      "category": "知識"
    },
    {
      "code": "K20",
      "name": "廢棄物管理辦法",
      "category": "知識"
    }
  ],
  "competency_skills": [
    {
      "code": "S01",
      "name": "陽極處理機台設備操作能力",
      "category": "技能"
    },
    {
      "code": "S02",
      "name": "機械設備與保養能力",
      "category": "技能"
    },
    {
      "code": "S03",
      "name": "設備故障通報能力",
      "category": "技能"
    },
    {
      "code": "S04",
      "name": "日常檢查及異常狀況初步研判能力",
      "category": "技能"
    },
    {
      "code": "S05",
      "name": "安全設施的防護與操作能力",
      "category": "技能"
    },
    {
      "code": "S06",
      "name": "清潔料件的能力",
      "category": "技能"
    },
    {
      "code": "S07",
      "name": "量測能力",
      "category": "技能"
    },
    {
      "code": "S08",
      "name": "陽極處理液、前處理液、添加劑的使用、充填、調整能力",
      "category": "技能"
    },
    {
      "code": "S09",
      "name": "料件吊掛的操作能力",
      "category": "技能"
    },
    {
      "code": "S10",
      "name": "人機介面的操作與參數設定能力",
      "category": "技能"
    },
    {
      "code": "S11",
      "name": "成品尺寸的量測能力",
      "category": "技能"
    },
    {
      "code": "S12",
      "name": "廢棄物與廢液處理能力",
      "category": "技能"
    }
  ],
  "competency_attitudes": [
    {
      "code": "A01",
      "name": "持續學習",
      "description": "能夠展現自我提升的企圖心，利用且積極參與各種機會，學習任務所需的新知識與技能，並能有效應用在特定任務。",
      "category": "態度"
    },
    {
      "code": "A02",
      "name": "主動積極",
      "description": "不需他人指示或要求能自動自發做事，面臨問題立即採取行動加以解決，且為達目標願意主動承擔額外責任。",
      "category": "態度"
    },
    {
      "code": "A03",
      "name": "自我管理",
      "description": "設立定義明確且實際可行的個人目標；對於及時完成任務展現高度進取、努力、承諾及負責任的行為。",
      "category": "態度"
    },
    {
      "code": "A04",
      "name": "團隊意識",
      "description": "積極參與並支持團隊，能彼此鼓勵共同達成團隊目標。",
      "category": "態度"
    },
    {
      "code": "A05",
      "name": "謹慎細心",
      "description": "對於任務的執行過程，能謹慎考量及處理所有細節，精確地檢視每個程序，並持續對其保持高度關注。",
      "category": "態度"
    },
    {
      "code": "A06",
      "name": "壓力容忍",
      "description": "冷靜且有效地應對及處理高度緊張的情況或壓力，如緊迫的時間、不友善的人、各類突發事件及危急狀況，並能以適當的方式紓解自身壓力。",
      "category": "態度"
    }
  ],
  "chunks_for_rag": [
    {
      "id": "basic_info",
      "type": "基本資訊",
      "content": "職能基準：陽極處理生產設備整備\n代碼：MPM8122-005v2\n版本：V2\n職類別：製造／生產管理（代碼：MPM）\n職業別：金屬表面處理機械操作人員（代碼：8122）\n行業別：製造業／金屬手工具及模具製造業（代碼：C2512）\n基準級別：3\n工作描述：從事陽極處理設備操作、維護及保養等工作。\n建議條件：\n更新日期：2024/12/15",
      "metadata": {
        "code": "MPM8122-005v2",
        "name": "陽極處理生產設備整備",
        "level": 3,
        "chunk_type": "overview"
      }
    },
    {
      "id": "task_T1.1",
      "type": "工作任務",
      "content": "主要職責：T1陽極處理生產設備整備作業\n任務編號：T1.1\n任務名稱：設備啟動與清潔作業\n職能級別：3\n工作產出：機台保養紀錄表\n\n行為指標：\n- 檢查陽極處理設備之動態機構行程是否有障礙物或不順暢。\n- 依正確的操作程序啟動設備電源開關。\n- 執行陽極處理設備清潔保養作業。\n\n所需知識（3項）：\n- 陽極處理機台設備的運作原理、規格\n- 陽極處理設備清潔與保養注意事項\n- 標準作業程序\n\n所需技能（4項）：\n- 陽極處理機台設備操作能力\n- 機械設備與保養能力\n- 設備故障通報能力\n- 日常檢查及異常狀況初步研判能力",
      "metadata": {
        "task_id": "T1.1",
        "task_name": "設備啟動與清潔作業",
        "main_responsibility": "T1陽極處理生產設備整備作業",
        "code": "MPM8122-005v2",
        "level": 3,
        "chunk_type": "task"
      }
    },
    {
      "id": "task_T1.2",
      "type": "工作任務",
      "content": "主要職責：T1陽極處理生產設備整備作業\n任務編號：T1.2\n任務名稱：執行安全檢查作業\n職能級別：3\n工作產出：無特定產出\n\n行為指標：\n- 瞭解製程產生的有害物質對人體造成的影響，並能做好適切的防護措施。\n- 執行陽極處理設備安全檢查及防護作業。\n- 製程中隨時監看設備運作，並掌握製程狀態與工作安全。\n\n所需知識（3項）：\n- 安全設施認知與作業程序規範\n- 陽極處理機台設備操作安全\n- 職業安全與衛生相關規範\n\n所需技能（3項）：\n- 陽極處理機台設備操作能力\n- 設備故障通報能力\n- 安全設施的防護與操作能力",
      "metadata": {
        "task_id": "T1.2",
        "task_name": "執行安全檢查作業",
        "main_responsibility": "T1陽極處理生產設備整備作業",
        "code": "MPM8122-005v2",
        "level": 3,
        "chunk_type": "task"
      }
    },
    {
      "id": "task_T2.1",
      "type": "工作任務",
      "content": "主要職責：T2陽極處理產線設備操作\n任務編號：T2.1\n任務名稱：熟練機台操作\n職能級別：3\n工作產出：無特定產出\n\n行為指標：\n- 熟練機台的操作。\n- 熟練操作人機介面的參數設定與調整\n- 依製令之製程規範落實執行與管控。\n\n所需知識（4項）：\n- 陽極處理機台設備的運作原理、規格\n- 料件吊掛注意事項\n- 人機介面的功能參數規範\n- 品質管理概論\n\n所需技能（4項）：\n- 機械設備與保養能力\n- 安全設施的防護與操作能力\n- 料件吊掛的操作能力\n- 人機介面的操作與參數設定能力",
      "metadata": {
        "task_id": "T2.1",
        "task_name": "熟練機台操作",
        "main_responsibility": "T2陽極處理產線設備操作",
        "code": "MPM8122-005v2",
        "level": 3,
        "chunk_type": "task"
      }
    },
    {
      "id": "task_T2.2",
      "type": "工作任務",
      "content": "主要職責：T2陽極處理產線設備操作\n任務編號：T2.2\n任務名稱：製程參數設定\n職能級別：3\n工作產出：無特定產出\n\n行為指標：\n- 依製造程序書及製程參數表使用正確的製程處理液、添加劑，以正確掌握陽極處理操作時的成分和濃度。\n- 依製令要求或成品規格設定時間、元素、溫度、濃度之相關參數設定。\n\n所需知識（4項）：\n- 陽極處理液與前處理液的功能與特性\n- 添加劑的功能與特性\n- 人機介面的功能參數規範\n- 電化學反應概論\n\n所需技能（2項）：\n- 陽極處理液、前處理液、添加劑的使用、充填、調整能力\n- 人機介面的操作與參數設定能力",
      "metadata": {
        "task_id": "T2.2",
        "task_name": "製程參數設定",
        "main_responsibility": "T2陽極處理產線設備操作",
        "code": "MPM8122-005v2",
        "level": 3,
        "chunk_type": "task"
      }
    },
    {
      "id": "task_T3.1",
      "type": "工作任務",
      "content": "主要職責：T3小量生產作業與檢測\n任務編號：T3.1\n任務名稱：小量上料\n職能級別：3\n工作產出：無特定產出\n\n行為指標：\n- 小量材料上架並檢查料件吊掛位置是否合宜。\n- 確認料件吊架是否合適，並檢查料件夾持是否穩固。\n\n所需知識（2項）：\n- 夾(治)具概論\n- 料件吊掛注意事項\n\n所需技能（1項）：\n- 料件吊掛的操作能力",
      "metadata": {
        "task_id": "T3.1",
        "task_name": "小量上料",
        "main_responsibility": "T3小量生產作業與檢測",
        "code": "MPM8122-005v2",
        "level": 3,
        "chunk_type": "task"
      }
    },
    {
      "id": "task_T4.1",
      "type": "工作任務",
      "content": "主要職責：T4量產操作與保養維護\n任務編號：T4.1\n任務名稱：批量生產作業\n職能級別：3\n工作產出：成品\n\n行為指標：\n- 依樣品檢測後的優化參數進行設定，並注意設備在製程中的變異及調整。\n- 監看成品料件的特徵變異。\n- 定時進行成品料件的取樣與尺寸量測。\n- 執行設備的故障通報。\n- 配合品保部門成品檢測取樣作業。\n- 執行設備保養作業。\n\n所需知識（5項）：\n- 量測與檢驗規範\n- 夾(治)具概論\n- 料件吊掛注意事項\n- 料件表面處理後的特徵變異\n- 設備運作變異及調整注意事項\n\n所需技能（5項）：\n- 日常檢查及異常狀況初步研判能力\n- 量測能力\n- 料件吊掛的操作能力\n- 人機介面的操作與參數設定能力\n- 成品尺寸的量測能力",
      "metadata": {
        "task_id": "T4.1",
        "task_name": "批量生產作業",
        "main_responsibility": "T4量產操作與保養維護",
        "code": "MPM8122-005v2",
        "level": 3,
        "chunk_type": "task"
      }
    },
    {
      "id": "task_T4.2",
      "type": "工作任務",
      "content": "主要職責：T4量產操作與保養維護\n任務編號：T4.2\n任務名稱：廢棄物處理與保養維護\n職能級別：3\n工作產出：無特定產出\n\n行為指標：\n- 依廠內廢棄物及廢液處理注意事項執行廢棄物及廢液的保存及處理。\n- 執行生產時每日保養作業及定期保養維護之操作。\n\n所需知識（3項）：\n- 陽極處理設備清潔與保養注意事項\n- 環保法規相關規範\n- 廢棄物管理辦法\n\n所需技能（3項）：\n- 機械設備與保養能力\n- 設備故障通報能力\n- 廢棄物與廢液處理能力",
      "metadata": {
        "task_id": "T4.2",
        "task_name": "廢棄物處理與保養維護",
        "main_responsibility": "T4量產操作與保養維護",
        "code": "MPM8122-005v2",
        "level": 3,
        "chunk_type": "task"
      }
    },
    {
      "id": "knowledge_skills_1",
      "type": "知識技能",
      "content": "職責領域：T1陽極處理生產設備整備作業\n\n需具備知識（6項）：\n- K01: 陽極處理機台設備的運作原理、規格\n- K02: 陽極處理設備清潔與保養注意事項\n- K03: 標準作業程序\n- K04: 安全設施認知與作業程序規範\n- K05: 陽極處理機台設備操作安全\n- K06: 職業安全與衛生相關規範\n\n需具備技能（5項）：\n- S01: 陽極處理機台設備操作能力\n- S02: 機械設備與保養能力\n- S03: 設備故障通報能力\n- S04: 日常檢查及異常狀況初步研判能力\n- S05: 安全設施的防護與操作能力",
      "metadata": {
        "main_responsibility": "T1陽極處理生產設備整備作業",
        "code": "MPM8122-005v2",
        "chunk_type": "knowledge_skills"
      }
    },
    {
      "id": "knowledge_skills_2",
      "type": "知識技能",
      "content": "職責領域：T2陽極處理產線設備操作\n\n需具備知識（7項）：\n- K01: 陽極處理機台設備的運作原理、規格\n- K09: 陽極處理液與前處理液的功能與特性\n- K10: 添加劑的功能與特性\n- K12: 料件吊掛注意事項\n- K13: 人機介面的功能參數規範\n- K14: 品質管理概論\n- K15: 電化學反應概論\n\n需具備技能（5項）：\n- S02: 機械設備與保養能力\n- S05: 安全設施的防護與操作能力\n- S08: 陽極處理液、前處理液、添加劑的使用、充填、調整能力\n- S09: 料件吊掛的操作能力\n- S10: 人機介面的操作與參數設定能力",
      "metadata": {
        "main_responsibility": "T2陽極處理產線設備操作",
        "code": "MPM8122-005v2",
        "chunk_type": "knowledge_skills"
      }
    },
    {
      "id": "knowledge_skills_3",
      "type": "知識技能",
      "content": "職責領域：T3小量生產作業與檢測\n\n需具備知識（2項）：\n- K11: 夾(治)具概論\n- K12: 料件吊掛注意事項\n\n需具備技能（1項）：\n- S09: 料件吊掛的操作能力",
      "metadata": {
        "main_responsibility": "T3小量生產作業與檢測",
        "code": "MPM8122-005v2",
        "chunk_type": "knowledge_skills"
      }
    },
    {
      "id": "knowledge_skills_4",
      "type": "知識技能",
      "content": "職責領域：T4量產操作與保養維護\n\n需具備知識（8項）：\n- K02: 陽極處理設備清潔與保養注意事項\n- K08: 量測與檢驗規範\n- K11: 夾(治)具概論\n- K12: 料件吊掛注意事項\n- K17: 料件表面處理後的特徵變異\n- K18: 設備運作變異及調整注意事項\n- K19: 環保法規相關規範\n- K20: 廢棄物管理辦法\n\n需具備技能（8項）：\n- S02: 機械設備與保養能力\n- S03: 設備故障通報能力\n- S04: 日常檢查及異常狀況初步研判能力\n- S07: 量測能力\n- S09: 料件吊掛的操作能力\n- S10: 人機介面的操作與參數設定能力\n- S11: 成品尺寸的量測能力\n- S12: 廢棄物與廢液處理能力",
      "metadata": {
        "main_responsibility": "T4量產操作與保養維護",
        "code": "MPM8122-005v2",
        "chunk_type": "knowledge_skills"
      }
    },
    {
      "id": "attitudes",
      "type": "職能態度",
      "content": "職能態度要求（6項）：\n\nA01 - 持續學習：能夠展現自我提升的企圖心，利用且積極參與各種機會，學習任務所需的新知識與技能，並能有效應用在特定任務。\n\nA02 - 主動積極：不需他人指示或要求能自動自發做事，面臨問題立即採取行動加以解決，且為達目標願意主動承擔額外責任。\n\nA03 - 自我管理：設立定義明確且實際可行的個人目標；對於及時完成任務展現高度進取、努力、承諾及負責任的行為。\n\nA04 - 團隊意識：積極參與並支持團隊，能彼此鼓勵共同達成團隊目標。\n\nA05 - 謹慎細心：對於任務的執行過程，能謹慎考量及處理所有細節，精確地檢視每個程序，並持續對其保持高度關注。\n\nA06 - 壓力容忍：冷靜且有效地應對及處理高度緊張的情況或壓力，如緊迫的時間、不友善的人、各類突發事件及危急狀況，並能以適當的方式紓解自身壓力。",
      "metadata": {
        "code": "MPM8122-005v2",
        "count": 6,
        "chunk_type": "attitudes"
      }
    },
    {
      "id": "summary",
      "type": "完整摘要",
      "content": "【陽極處理生產設備整備職能基準摘要】\n\n一、基本資訊\n- 職能代碼：MPM8122-005v2\n- 職類別：製造／生產管理\n- 職業別：金屬表面處理機械操作人員\n- 基準級別：3\n\n二、工作描述\n從事陽極處理設備操作、維護及保養等工作。\n\n三、主要職責與任務（7項）\n- T1.1 設備啟動與清潔作業\n- T1.2 執行安全檢查作業\n- T2.1 熟練機台操作\n- T2.2 製程參數設定\n- T3.1 小量上料\n- T4.1 批量生產作業\n- T4.2 廢棄物處理與保養維護\n\n四、職能要求\n- 知識項目：20項\n- 技能項目：12項\n- 態度項目：6項\n\n五、建議條件\n",
      "metadata": {
        "code": "MPM8122-005v2",
        "name": "陽極處理生產設備整備",
        "chunk_type": "summary"
      }
    }
  ],
  "parse_success": true,
  "parse_errors": []
}