{
  "metadata": {
    "code": "NFP7919-002v4",
    "name": "食品加工製程管理人員",
    "update_date": "2023/12/15",
    "version": "V4",
    "status": "最新版本",
    "source_file": "C:\\Users\\User\\Graph_RAG_test\\data\\raw_pdf\\食品加工製程管理人員-職能基準.pdf"
  },
  "basic_info": {
    "category": "天然資源、食品與農業／食品生產與加工",
    "category_code": "NFP",
    "occupation": "其他食品製造及有關工作人員",
    "occupation_code": "7919",
    "industry": [
      "製造業／食品及飼品製造業"
    ],
    "industry_code": [
      "C08"
    ],
    "job_description": "規劃、維護及管理食品加工製程所需之相關生產資源。",
    "level": 4,
    "requirements": "大專以上食品相關科系畢業，且具1年以上食品加工生產相關經歷或高中（職）以上相關科系畢業，且具3年以上食品加工生產相關經歷。"
  },
  "competency_tasks": [
    {
      "main_responsibility": "T1規劃與協調製程管理維護作業",
      "task_id": "T1.1",
      "task_name": "檢核製程管理維護規範",
      "output": "維護規範計畫",
      "behaviors": [
        "遵循法規及程序【註1】，檢核維護生產、製程、設備、製程管理之方法與執行維護所需資源，評估設備及製程維護規範計畫，優先處理特殊維護規範，並提出建議。"
      ],
      "knowledge": [
        "K01",
        "K02",
        "K03",
        "K04",
        "K05",
        "K06"
      ],
      "skills": [
        "S01",
        "S02",
        "S03"
      ],
      "level": 4
    },
    {
      "main_responsibility": "T1規劃與協調製程管理維護作業",
      "task_id": "T1.2",
      "task_name": "規劃製程管理維護作業",
      "output": "維護作業計畫表",
      "behaviors": [
        "遵循法規及程序，依據生產時間、設備功能、製程管理、特殊維護規範、及使用資源和工作環境守則，規劃維護作業計畫表，制定設備績效，降低生產阻礙。",
        "依據組織規範紀錄維護時程表。",
        "諮詢受維護區域工作人員之建議，溝通並確定維護工作的時程及內容。"
      ],
      "knowledge": [
        "K01",
        "K02",
        "K03",
        "K04",
        "K05",
        "K06"
      ],
      "skills": [
        "S01",
        "S02",
        "S03",
        "S04",
        "S05",
        "S06"
      ],
      "level": 4
    },
    {
      "main_responsibility": "T1規劃與協調製程管理維護作業",
      "task_id": "T1.3",
      "task_name": "監控製程管理維護作業與控制",
      "output": "維護改善計畫",
      "behaviors": [
        "遵循法規及程序，監控維護工作，檢核現況與維護時程之差異，評估影響維護作業計畫之非預期事件。",
        "即時與相關人士檢核、溝通維護作業計畫之缺失，研討改善措施。"
      ],
      "knowledge": [
        "K01",
        "K02",
        "K03",
        "K04",
        "K05",
        "K06"
      ],
      "skills": [
        "S01",
        "S02",
        "S03",
        "S06",
        "S07"
      ],
      "level": 4
    },
    {
      "main_responsibility": "T3應用與檢核食品加工技術",
      "task_id": "T3.1",
      "task_name": "監督各類食品加工作業",
      "output": "測試/評估紀錄",
      "behaviors": [
        "遵循法規及程序，檢核各類食品加工製程之原物料、設備。",
        "應用、測試與評估並監督各類食品加工製程及生產作業過程。"
      ],
      "knowledge": [
        "K01",
        "K02",
        "K04",
        "K05",
        "K08"
      ],
      "skills": [
        "S01",
        "S10",
        "S11"
      ],
      "level": 45
    },
    {
      "main_responsibility": "T4管理食品加工作業",
      "task_id": "T4.1",
      "task_name": "確認生產流程",
      "output": null,
      "behaviors": [
        "遵循法規及程序，確認食品生產流程設備、特性與操作原則。",
        "制定特定生產流程設備與配件之操作標準和維修條件，檢核產品特性和常見變化，進行調整。"
      ],
      "knowledge": [
        "K01",
        "K02",
        "K03",
        "K05",
        "K07",
        "K08"
      ],
      "skills": [
        "S01",
        "S10",
        "S11",
        "S14"
      ],
      "level": 4
    },
    {
      "main_responsibility": "T4管理食品加工作業",
      "task_id": "T4.2",
      "task_name": "監控食品生產",
      "output": null,
      "behaviors": [
        "遵循法規及程序，執行製程危害分析與重要管制計劃，監管各類型管控機制之操作方式與管控模式。",
        "遵循法規及程序，確認生產資料、需求和蒐集相關資料。",
        "遵循法規及程序，改善不合格成品與處理程序。"
      ],
      "knowledge": [
        "K01",
        "K02",
        "K05",
        "K07",
        "K08"
      ],
      "skills": [
        "S01",
        "S10",
        "S11",
        "S14"
      ],
      "level": 4
    },
    {
      "main_responsibility": "T5運用食品包裝技術",
      "task_id": "T5.1",
      "task_name": "選用食品包裝",
      "output": "產品包裝規格檢核表",
      "behaviors": [
        "遵循法規及程序，選用合格的食品包裝材料；確認食品與包裝材料的接觸合乎規範。",
        "遵循法規及程序，處理包裝材料，確認對環境並無造成影響。"
      ],
      "knowledge": [
        "K01",
        "K02",
        "K05",
        "K07",
        "K10"
      ],
      "skills": [
        "S01",
        "S12",
        "S16"
      ],
      "level": 3
    },
    {
      "main_responsibility": "T6協同設備保修",
      "task_id": "T6.1",
      "task_name": "訂定預防保修計畫",
      "output": "預防保修計畫書",
      "behaviors": [
        "遵循法規及程序，蒐集保養供應內外部資源，制定例行性保修，並將非例行性之保養納入保養計畫。",
        "遵循法規及程序，計算保修工作之成本。",
        "遵循法規及程序，以量測控制執行中的危害，紀錄生產解析、過程和程序。",
        "監督保修工作之整潔。"
      ],
      "knowledge": [
        "K01",
        "K02",
        "K03",
        "K04",
        "K05"
      ],
      "skills": [
        "S01",
        "S19",
        "S03",
        "S04",
        "S05",
        "S13",
        "S17"
      ],
      "level": 4
    },
    {
      "main_responsibility": "T6協同設備保修",
      "task_id": "T6.2",
      "task_name": "製定保修作業排程",
      "output": "保修作業表、教育訓練記錄",
      "behaviors": [
        "遵循法規及程序，規劃保修工作，並運用資源，以符合生產要求。",
        "遵循法規及程序，選用保修專業人員並安排適當的訓練及必要的評量。",
        "遵循法規及程序，配合生產要求，安排保修時程與工作。"
      ],
      "knowledge": [
        "K01",
        "K02",
        "K03",
        "K04",
        "K05"
      ],
      "skills": [
        "S01",
        "S04",
        "S05",
        "S18"
      ],
      "level": 4
    },
    {
      "main_responsibility": "T6協同設備保修",
      "task_id": "T6.3",
      "task_name": "執行保修計畫",
      "output": "需求表、排班表",
      "behaviors": [
        "遵循法規及程序，確定需要的資源（包含裝備、人員和耗材）以完成保養計劃。",
        "遵循法規及程序，確定並協調耗材的供給與設備，必要時購買裝備、耗材，指派專業人員負責維修，以符合計劃的需求。"
      ],
      "knowledge": [
        "K01",
        "K02",
        "K03",
        "K04",
        "K05"
      ],
      "skills": [
        "S01",
        "S05",
        "S17",
        "S19"
      ],
      "level": 4
    },
    {
      "main_responsibility": "T7提高生產效能",
      "task_id": "T7.1",
      "task_name": "優化生產製程",
      "output": "生產製程改善提案",
      "behaviors": [
        "遵循法規及程序，應用優化之生產作業，讓產品品質與團隊績效達到最佳程度。",
        "遵循法規及程序，應用優化之生產作業，提高顧客效益，縮短交貨時間。",
        "遵循法規及程序，與利害關係人協調並解決突發狀況與其他衝突。",
        "遵循法規及程序，檢核改善方案，優化生產系統與流程，達成生產作業之最大效益。"
      ],
      "knowledge": [
        "K01",
        "K02",
        "K03",
        "K04",
        "K05",
        "K07",
        "K10"
      ],
      "skills": [
        "S01",
        "S05",
        "S07",
        "S08",
        "S09",
        "S10",
        "S11",
        "S20",
        "S21"
      ],
      "level": 4
    },
    {
      "main_responsibility": "T7提高生產效能",
      "task_id": "T7.2",
      "task_name": "實施改善",
      "output": "改善檢核表",
      "behaviors": [
        "遵循法規及程序，執行改善方案，檢核整體系統之改善成效，避免造成非預期結果。",
        "遵循法規及程序，監督改善作業，並依據"
      ],
      "knowledge": [
        "K01",
        "K02",
        "K03",
        "K04",
        "K05",
        "K07",
        "K10"
      ],
      "skills": [
        "S01",
        "S05",
        "S08",
        "S09",
        "S10",
        "S11",
        "S21"
      ],
      "level": 4
    }
  ],
  "competency_knowledge": [
    {
      "code": "K01",
      "name": "食品安全衛生管理相關知識",
      "category": "知識"
    },
    {
      "code": "K02",
      "name": "職業安全衛生相關知識",
      "category": "知識"
    },
    {
      "code": "K03",
      "name": "製程設備維護相關知識",
      "category": "知識"
    },
    {
      "code": "K04",
      "name": "品質管理相關知識【註2】",
      "category": "知識"
    },
    {
      "code": "K05",
      "name": "ISO22000相關知識",
      "category": "知識"
    },
    {
      "code": "K06",
      "name": "組織政策",
      "category": "知識"
    },
    {
      "code": "K07",
      "name": "食品製程相關知識",
      "category": "知識"
    },
    {
      "code": "K08",
      "name": "各類食品原料與加工知識",
      "category": "知識"
    },
    {
      "code": "K09",
      "name": "成本概論",
      "category": "知識"
    },
    {
      "code": "K10",
      "name": "食品包裝相關知識",
      "category": "知識"
    }
  ],
  "competency_skills": [
    {
      "code": "S01",
      "name": "依標準作業流程執行【註3】",
      "category": "技能"
    },
    {
      "code": "S02",
      "name": "維護方法與資源檢核",
      "category": "技能"
    },
    {
      "code": "S03",
      "name": "維護規範評估/建議",
      "category": "技能"
    },
    {
      "code": "S04",
      "name": "維護計畫制定",
      "category": "技能"
    },
    {
      "code": "S05",
      "name": "完成文件記錄",
      "category": "技能"
    },
    {
      "code": "S06",
      "name": "工作人員諮詢/溝通",
      "category": "技能"
    },
    {
      "code": "S07",
      "name": "改善計畫制定",
      "category": "技能"
    },
    {
      "code": "S08",
      "name": "數據蒐集運用",
      "category": "技能"
    },
    {
      "code": "S09",
      "name": "統計分析應用",
      "category": "技能"
    },
    {
      "code": "S10",
      "name": "原物料/設備檢核",
      "category": "技能"
    },
    {
      "code": "S11",
      "name": "食品加工監督",
      "category": "技能"
    },
    {
      "code": "S12",
      "name": "環境影響評估",
      "category": "技能"
    },
    {
      "code": "S13",
      "name": "計算成本",
      "category": "技能"
    },
    {
      "code": "S14",
      "name": "生產/維修作業調整與改善",
      "category": "技能"
    },
    {
      "code": "S15",
      "name": "相關規定解說",
      "category": "技能"
    },
    {
      "code": "S16",
      "name": "合格包裝材料應用處理",
      "category": "技能"
    },
    {
      "code": "S19",
      "name": "保修方法與資源檢核",
      "category": "技能"
    },
    {
      "code": "S17",
      "name": "保修作業監督",
      "category": "技能"
    },
    {
      "code": "S18",
      "name": "執行教育訓練",
      "category": "技能"
    },
    {
      "code": "S20",
      "name": "溝通協調",
      "category": "技能"
    },
    {
      "code": "S21",
      "name": "生產作業優化",
      "category": "技能"
    }
  ],
  "competency_attitudes": [
    {
      "code": "A01",
      "name": "主動積極",
      "description": "設定明確目標，不需他人指示或要求能自動自發做事，面臨問題立即採取行動加以解決，且為達目標願意主動承擔額外責任。",
      "category": "態度"
    },
    {
      "code": "A02",
      "name": "自我管理",
      "description": "設立定義明確且實際可行的個人目標；對於及時完成任務展現高度進取、努力、承諾及負責任的行為。",
      "category": "態度"
    },
    {
      "code": "A03",
      "name": "團隊意識",
      "description": "積極參與並支持團隊，能彼此鼓勵共同達成團隊目標。",
      "category": "態度"
    },
    {
      "code": "A04",
      "name": "親和力",
      "description": "對他人表現理解、友善、同理心、關心和禮貌，並能與不同背景的人發展及維持良好關係。",
      "category": "態度"
    },
    {
      "code": "A05",
      "name": "壓力容忍",
      "description": "冷靜且有效地應對及處理高度緊張的情況或壓力，如緊迫的時間、不友善的人、各類突發事件及危急狀況，並能以適當的方式紓解自身壓力。",
      "category": "態度"
    }
  ],
  "chunks_for_rag": [
    {
      "id": "basic_info",
      "type": "基本資訊",
      "content": "職能基準：規劃與協調製程管理維\n代碼：NFP7919-002v4\n版本：V4\n職類別：天然資源、食品與農業／食品生產與加工（代碼：NFP）\n職業別：其他食品製造及有關工作人員（代碼：7919）\n行業別：製造業／食品及飼品製造業（代碼：C08）\n基準級別：4\n工作描述：規劃、維護及管理食品加工製程所需之相關生產資源。\n建議條件：大專以上食品相關科系畢業，且具1年以上食品加工生產相關經歷或高中（職）以上相關科系畢業，且具3年以上食品加工生產相關經歷。\n更新日期：2023/12/15",
      "metadata": {
        "code": "NFP7919-002v4",
        "name": "規劃與協調製程管理維",
        "level": 4,
        "chunk_type": "overview"
      }
    },
    {
      "id": "task_T1.1",
      "type": "工作任務",
      "content": "主要職責：T1規劃與協調製程管理維護作業\n任務編號：T1.1\n任務名稱：檢核製程管理維護規範\n職能級別：4\n工作產出：維護規範計畫\n\n行為指標：\n- 遵循法規及程序【註1】，檢核維護生產、製程、設備、製程管理之方法與執行維護所需資源，評估設備及製程維護規範計畫，優先處理特殊維護規範，並提出建議。\n\n所需知識（6項）：\n- 食品安全衛生管理相關知識\n- 職業安全衛生相關知識\n- 製程設備維護相關知識\n- 品質管理相關知識【註2】\n- ISO22000相關知識\n- 組織政策\n\n所需技能（3項）：\n- 依標準作業流程執行【註3】\n- 維護方法與資源檢核\n- 維護規範評估/建議",
      "metadata": {
        "task_id": "T1.1",
        "task_name": "檢核製程管理維護規範",
        "main_responsibility": "T1規劃與協調製程管理維護作業",
        "code": "NFP7919-002v4",
        "level": 4,
        "chunk_type": "task"
      }
    },
    {
      "id": "task_T1.2",
      "type": "工作任務",
      "content": "主要職責：T1規劃與協調製程管理維護作業\n任務編號：T1.2\n任務名稱：規劃製程管理維護作業\n職能級別：4\n工作產出：維護作業計畫表\n\n行為指標：\n- 遵循法規及程序，依據生產時間、設備功能、製程管理、特殊維護規範、及使用資源和工作環境守則，規劃維護作業計畫表，制定設備績效，降低生產阻礙。\n- 依據組織規範紀錄維護時程表。\n- 諮詢受維護區域工作人員之建議，溝通並確定維護工作的時程及內容。\n\n所需知識（6項）：\n- 食品安全衛生管理相關知識\n- 職業安全衛生相關知識\n- 製程設備維護相關知識\n- 品質管理相關知識【註2】\n- ISO22000相關知識\n- 組織政策\n\n所需技能（6項）：\n- 依標準作業流程執行【註3】\n- 維護方法與資源檢核\n- 維護規範評估/建議\n- 維護計畫制定\n- 完成文件記錄\n- 工作人員諮詢/溝通",
      "metadata": {
        "task_id": "T1.2",
        "task_name": "規劃製程管理維護作業",
        "main_responsibility": "T1規劃與協調製程管理維護作業",
        "code": "NFP7919-002v4",
        "level": 4,
        "chunk_type": "task"
      }
    },
    {
      "id": "task_T1.3",
      "type": "工作任務",
      "content": "主要職責：T1規劃與協調製程管理維護作業\n任務編號：T1.3\n任務名稱：監控製程管理維護作業與控制\n職能級別：4\n工作產出：維護改善計畫\n\n行為指標：\n- 遵循法規及程序，監控維護工作，檢核現況與維護時程之差異，評估影響維護作業計畫之非預期事件。\n- 即時與相關人士檢核、溝通維護作業計畫之缺失，研討改善措施。\n\n所需知識（6項）：\n- 食品安全衛生管理相關知識\n- 職業安全衛生相關知識\n- 製程設備維護相關知識\n- 品質管理相關知識【註2】\n- ISO22000相關知識\n- 組織政策\n\n所需技能（5項）：\n- 依標準作業流程執行【註3】\n- 維護方法與資源檢核\n- 維護規範評估/建議\n- 工作人員諮詢/溝通\n- 改善計畫制定",
      "metadata": {
        "task_id": "T1.3",
        "task_name": "監控製程管理維護作業與控制",
        "main_responsibility": "T1規劃與協調製程管理維護作業",
        "code": "NFP7919-002v4",
        "level": 4,
        "chunk_type": "task"
      }
    },
    {
      "id": "task_T3.1",
      "type": "工作任務",
      "content": "主要職責：T3應用與檢核食品加工技術\n任務編號：T3.1\n任務名稱：監督各類食品加工作業\n職能級別：45\n工作產出：測試/評估紀錄\n\n行為指標：\n- 遵循法規及程序，檢核各類食品加工製程之原物料、設備。\n- 應用、測試與評估並監督各類食品加工製程及生產作業過程。\n\n所需知識（5項）：\n- 食品安全衛生管理相關知識\n- 職業安全衛生相關知識\n- 品質管理相關知識【註2】\n- ISO22000相關知識\n- 各類食品原料與加工知識\n\n所需技能（3項）：\n- 依標準作業流程執行【註3】\n- 原物料/設備檢核\n- 食品加工監督",
      "metadata": {
        "task_id": "T3.1",
        "task_name": "監督各類食品加工作業",
        "main_responsibility": "T3應用與檢核食品加工技術",
        "code": "NFP7919-002v4",
        "level": 45,
        "chunk_type": "task"
      }
    },
    {
      "id": "task_T4.1",
      "type": "工作任務",
      "content": "主要職責：T4管理食品加工作業\n任務編號：T4.1\n任務名稱：確認生產流程\n職能級別：4\n工作產出：無特定產出\n\n行為指標：\n- 遵循法規及程序，確認食品生產流程設備、特性與操作原則。\n- 制定特定生產流程設備與配件之操作標準和維修條件，檢核產品特性和常見變化，進行調整。\n\n所需知識（6項）：\n- 食品安全衛生管理相關知識\n- 職業安全衛生相關知識\n- 製程設備維護相關知識\n- ISO22000相關知識\n- 食品製程相關知識\n- 各類食品原料與加工知識\n\n所需技能（4項）：\n- 依標準作業流程執行【註3】\n- 原物料/設備檢核\n- 食品加工監督\n- 生產/維修作業調整與改善",
      "metadata": {
        "task_id": "T4.1",
        "task_name": "確認生產流程",
        "main_responsibility": "T4管理食品加工作業",
        "code": "NFP7919-002v4",
        "level": 4,
        "chunk_type": "task"
      }
    },
    {
      "id": "task_T4.2",
      "type": "工作任務",
      "content": "主要職責：T4管理食品加工作業\n任務編號：T4.2\n任務名稱：監控食品生產\n職能級別：4\n工作產出：無特定產出\n\n行為指標：\n- 遵循法規及程序，執行製程危害分析與重要管制計劃，監管各類型管控機制之操作方式與管控模式。\n- 遵循法規及程序，確認生產資料、需求和蒐集相關資料。\n- 遵循法規及程序，改善不合格成品與處理程序。\n\n所需知識（5項）：\n- 食品安全衛生管理相關知識\n- 職業安全衛生相關知識\n- ISO22000相關知識\n- 食品製程相關知識\n- 各類食品原料與加工知識\n\n所需技能（4項）：\n- 依標準作業流程執行【註3】\n- 原物料/設備檢核\n- 食品加工監督\n- 生產/維修作業調整與改善",
      "metadata": {
        "task_id": "T4.2",
        "task_name": "監控食品生產",
        "main_responsibility": "T4管理食品加工作業",
        "code": "NFP7919-002v4",
        "level": 4,
        "chunk_type": "task"
      }
    },
    {
      "id": "task_T5.1",
      "type": "工作任務",
      "content": "主要職責：T5運用食品包裝技術\n任務編號：T5.1\n任務名稱：選用食品包裝\n職能級別：3\n工作產出：產品包裝規格檢核表\n\n行為指標：\n- 遵循法規及程序，選用合格的食品包裝材料；確認食品與包裝材料的接觸合乎規範。\n- 遵循法規及程序，處理包裝材料，確認對環境並無造成影響。\n\n所需知識（5項）：\n- 食品安全衛生管理相關知識\n- 職業安全衛生相關知識\n- ISO22000相關知識\n- 食品製程相關知識\n- 食品包裝相關知識\n\n所需技能（3項）：\n- 依標準作業流程執行【註3】\n- 環境影響評估\n- 合格包裝材料應用處理",
      "metadata": {
        "task_id": "T5.1",
        "task_name": "選用食品包裝",
        "main_responsibility": "T5運用食品包裝技術",
        "code": "NFP7919-002v4",
        "level": 3,
        "chunk_type": "task"
      }
    },
    {
      "id": "task_T6.1",
      "type": "工作任務",
      "content": "主要職責：T6協同設備保修\n任務編號：T6.1\n任務名稱：訂定預防保修計畫\n職能級別：4\n工作產出：預防保修計畫書\n\n行為指標：\n- 遵循法規及程序，蒐集保養供應內外部資源，制定例行性保修，並將非例行性之保養納入保養計畫。\n- 遵循法規及程序，計算保修工作之成本。\n- 遵循法規及程序，以量測控制執行中的危害，紀錄生產解析、過程和程序。\n- 監督保修工作之整潔。\n\n所需知識（5項）：\n- 食品安全衛生管理相關知識\n- 職業安全衛生相關知識\n- 製程設備維護相關知識\n- 品質管理相關知識【註2】\n- ISO22000相關知識\n\n所需技能（7項）：\n- 依標準作業流程執行【註3】\n- 保修方法與資源檢核\n- 維護規範評估/建議\n- 維護計畫制定\n- 完成文件記錄\n- 計算成本\n- 保修作業監督",
      "metadata": {
        "task_id": "T6.1",
        "task_name": "訂定預防保修計畫",
        "main_responsibility": "T6協同設備保修",
        "code": "NFP7919-002v4",
        "level": 4,
        "chunk_type": "task"
      }
    },
    {
      "id": "task_T6.2",
      "type": "工作任務",
      "content": "主要職責：T6協同設備保修\n任務編號：T6.2\n任務名稱：製定保修作業排程\n職能級別：4\n工作產出：保修作業表、教育訓練記錄\n\n行為指標：\n- 遵循法規及程序，規劃保修工作，並運用資源，以符合生產要求。\n- 遵循法規及程序，選用保修專業人員並安排適當的訓練及必要的評量。\n- 遵循法規及程序，配合生產要求，安排保修時程與工作。\n\n所需知識（5項）：\n- 食品安全衛生管理相關知識\n- 職業安全衛生相關知識\n- 製程設備維護相關知識\n- 品質管理相關知識【註2】\n- ISO22000相關知識\n\n所需技能（4項）：\n- 依標準作業流程執行【註3】\n- 維護計畫制定\n- 完成文件記錄\n- 執行教育訓練",
      "metadata": {
        "task_id": "T6.2",
        "task_name": "製定保修作業排程",
        "main_responsibility": "T6協同設備保修",
        "code": "NFP7919-002v4",
        "level": 4,
        "chunk_type": "task"
      }
    },
    {
      "id": "task_T6.3",
      "type": "工作任務",
      "content": "主要職責：T6協同設備保修\n任務編號：T6.3\n任務名稱：執行保修計畫\n職能級別：4\n工作產出：需求表、排班表\n\n行為指標：\n- 遵循法規及程序，確定需要的資源（包含裝備、人員和耗材）以完成保養計劃。\n- 遵循法規及程序，確定並協調耗材的供給與設備，必要時購買裝備、耗材，指派專業人員負責維修，以符合計劃的需求。\n\n所需知識（5項）：\n- 食品安全衛生管理相關知識\n- 職業安全衛生相關知識\n- 製程設備維護相關知識\n- 品質管理相關知識【註2】\n- ISO22000相關知識\n\n所需技能（4項）：\n- 依標準作業流程執行【註3】\n- 完成文件記錄\n- 保修作業監督\n- 保修方法與資源檢核",
      "metadata": {
        "task_id": "T6.3",
        "task_name": "執行保修計畫",
        "main_responsibility": "T6協同設備保修",
        "code": "NFP7919-002v4",
        "level": 4,
        "chunk_type": "task"
      }
    },
    {
      "id": "task_T7.1",
      "type": "工作任務",
      "content": "主要職責：T7提高生產效能\n任務編號：T7.1\n任務名稱：優化生產製程\n職能級別：4\n工作產出：生產製程改善提案\n\n行為指標：\n- 遵循法規及程序，應用優化之生產作業，讓產品品質與團隊績效達到最佳程度。\n- 遵循法規及程序，應用優化之生產作業，提高顧客效益，縮短交貨時間。\n- 遵循法規及程序，與利害關係人協調並解決突發狀況與其他衝突。\n- 遵循法規及程序，檢核改善方案，優化生產系統與流程，達成生產作業之最大效益。\n\n所需知識（7項）：\n- 食品安全衛生管理相關知識\n- 職業安全衛生相關知識\n- 製程設備維護相關知識\n- 品質管理相關知識【註2】\n- ISO22000相關知識\n- 食品製程相關知識\n- 食品包裝相關知識\n\n所需技能（9項）：\n- 依標準作業流程執行【註3】\n- 完成文件記錄\n- 改善計畫制定\n- 數據蒐集運用\n- 統計分析應用\n- 原物料/設備檢核\n- 食品加工監督\n- 溝通協調\n- 生產作業優化",
      "metadata": {
        "task_id": "T7.1",
        "task_name": "優化生產製程",
        "main_responsibility": "T7提高生產效能",
        "code": "NFP7919-002v4",
        "level": 4,
        "chunk_type": "task"
      }
    },
    {
      "id": "task_T7.2",
      "type": "工作任務",
      "content": "主要職責：T7提高生產效能\n任務編號：T7.2\n任務名稱：實施改善\n職能級別：4\n工作產出：改善檢核表\n\n行為指標：\n- 遵循法規及程序，執行改善方案，檢核整體系統之改善成效，避免造成非預期結果。\n- 遵循法規及程序，監督改善作業，並依據\n\n所需知識（7項）：\n- 食品安全衛生管理相關知識\n- 職業安全衛生相關知識\n- 製程設備維護相關知識\n- 品質管理相關知識【註2】\n- ISO22000相關知識\n- 食品製程相關知識\n- 食品包裝相關知識\n\n所需技能（7項）：\n- 依標準作業流程執行【註3】\n- 完成文件記錄\n- 數據蒐集運用\n- 統計分析應用\n- 原物料/設備檢核\n- 食品加工監督\n- 生產作業優化",
      "metadata": {
        "task_id": "T7.2",
        "task_name": "實施改善",
        "main_responsibility": "T7提高生產效能",
        "code": "NFP7919-002v4",
        "level": 4,
        "chunk_type": "task"
      }
    },
    {
      "id": "knowledge_skills_1",
      "type": "知識技能",
      "content": "職責領域：T1規劃與協調製程管理維護作業\n\n需具備知識（6項）：\n- K01: 食品安全衛生管理相關知識\n- K02: 職業安全衛生相關知識\n- K03: 製程設備維護相關知識\n- K04: 品質管理相關知識【註2】\n- K05: ISO22000相關知識\n- K06: 組織政策\n\n需具備技能（7項）：\n- S01: 依標準作業流程執行【註3】\n- S02: 維護方法與資源檢核\n- S03: 維護規範評估/建議\n- S04: 維護計畫制定\n- S05: 完成文件記錄\n- S06: 工作人員諮詢/溝通\n- S07: 改善計畫制定",
      "metadata": {
        "main_responsibility": "T1規劃與協調製程管理維護作業",
        "code": "NFP7919-002v4",
        "chunk_type": "knowledge_skills"
      }
    },
    {
      "id": "knowledge_skills_2",
      "type": "知識技能",
      "content": "職責領域：T3應用與檢核食品加工技術\n\n需具備知識（5項）：\n- K01: 食品安全衛生管理相關知識\n- K02: 職業安全衛生相關知識\n- K04: 品質管理相關知識【註2】\n- K05: ISO22000相關知識\n- K08: 各類食品原料與加工知識\n\n需具備技能（3項）：\n- S01: 依標準作業流程執行【註3】\n- S10: 原物料/設備檢核\n- S11: 食品加工監督",
      "metadata": {
        "main_responsibility": "T3應用與檢核食品加工技術",
        "code": "NFP7919-002v4",
        "chunk_type": "knowledge_skills"
      }
    },
    {
      "id": "knowledge_skills_3",
      "type": "知識技能",
      "content": "職責領域：T4管理食品加工作業\n\n需具備知識（6項）：\n- K01: 食品安全衛生管理相關知識\n- K02: 職業安全衛生相關知識\n- K03: 製程設備維護相關知識\n- K05: ISO22000相關知識\n- K07: 食品製程相關知識\n- K08: 各類食品原料與加工知識\n\n需具備技能（4項）：\n- S01: 依標準作業流程執行【註3】\n- S10: 原物料/設備檢核\n- S11: 食品加工監督\n- S14: 生產/維修作業調整與改善",
      "metadata": {
        "main_responsibility": "T4管理食品加工作業",
        "code": "NFP7919-002v4",
        "chunk_type": "knowledge_skills"
      }
    },
    {
      "id": "knowledge_skills_4",
      "type": "知識技能",
      "content": "職責領域：T5運用食品包裝技術\n\n需具備知識（5項）：\n- K01: 食品安全衛生管理相關知識\n- K02: 職業安全衛生相關知識\n- K05: ISO22000相關知識\n- K07: 食品製程相關知識\n- K10: 食品包裝相關知識\n\n需具備技能（3項）：\n- S01: 依標準作業流程執行【註3】\n- S12: 環境影響評估\n- S16: 合格包裝材料應用處理",
      "metadata": {
        "main_responsibility": "T5運用食品包裝技術",
        "code": "NFP7919-002v4",
        "chunk_type": "knowledge_skills"
      }
    },
    {
      "id": "knowledge_skills_5",
      "type": "知識技能",
      "content": "職責領域：T6協同設備保修\n\n需具備知識（5項）：\n- K01: 食品安全衛生管理相關知識\n- K02: 職業安全衛生相關知識\n- K03: 製程設備維護相關知識\n- K04: 品質管理相關知識【註2】\n- K05: ISO22000相關知識\n\n需具備技能（8項）：\n- S01: 依標準作業流程執行【註3】\n- S03: 維護規範評估/建議\n- S04: 維護計畫制定\n- S05: 完成文件記錄\n- S13: 計算成本\n- S17: 保修作業監督\n- S18: 執行教育訓練\n- S19: 保修方法與資源檢核",
      "metadata": {
        "main_responsibility": "T6協同設備保修",
        "code": "NFP7919-002v4",
        "chunk_type": "knowledge_skills"
      }
    },
    {
      "id": "knowledge_skills_6",
      "type": "知識技能",
      "content": "職責領域：T7提高生產效能\n\n需具備知識（7項）：\n- K01: 食品安全衛生管理相關知識\n- K02: 職業安全衛生相關知識\n- K03: 製程設備維護相關知識\n- K04: 品質管理相關知識【註2】\n- K05: ISO22000相關知識\n- K07: 食品製程相關知識\n- K10: 食品包裝相關知識\n\n需具備技能（9項）：\n- S01: 依標準作業流程執行【註3】\n- S05: 完成文件記錄\n- S07: 改善計畫制定\n- S08: 數據蒐集運用\n- S09: 統計分析應用\n- S10: 原物料/設備檢核\n- S11: 食品加工監督\n- S20: 溝通協調\n- S21: 生產作業優化",
      "metadata": {
        "main_responsibility": "T7提高生產效能",
        "code": "NFP7919-002v4",
        "chunk_type": "knowledge_skills"
      }
    },
    {
      "id": "attitudes",
      "type": "職能態度",
      "content": "職能態度要求（5項）：\n\nA01 - 主動積極：設定明確目標，不需他人指示或要求能自動自發做事，面臨問題立即採取行動加以解決，且為達目標願意主動承擔額外責任。\n\nA02 - 自我管理：設立定義明確且實際可行的個人目標；對於及時完成任務展現高度進取、努力、承諾及負責任的行為。\n\nA03 - 團隊意識：積極參與並支持團隊，能彼此鼓勵共同達成團隊目標。\n\nA04 - 親和力：對他人表現理解、友善、同理心、關心和禮貌，並能與不同背景的人發展及維持良好關係。\n\nA05 - 壓力容忍：冷靜且有效地應對及處理高度緊張的情況或壓力，如緊迫的時間、不友善的人、各類突發事件及危急狀況，並能以適當的方式紓解自身壓力。",
      "metadata": {
        "code": "NFP7919-002v4",
        "count": 5,
        "chunk_type": "attitudes"
      }
    },
    {
      "id": "summary",
      "type": "完整摘要",
      "content": "【規劃與協調製程管理維職能基準摘要】\n\n一、基本資訊\n- 職能代碼：NFP7919-002v4\n- 職類別：天然資源、食品與農業／食品生產與加工\n- 職業別：其他食品製造及有關工作人員\n- 基準級別：4\n\n二、工作描述\n規劃、維護及管理食品加工製程所需之相關生產資源。\n\n三、主要職責與任務（12項）\n- T1.1 檢核製程管理維護規範\n- T1.2 規劃製程管理維護作業\n- T1.3 監控製程管理維護作業與控制\n- T3.1 監督各類食品加工作業\n- T4.1 確認生產流程\n- T4.2 監控食品生產\n- T5.1 選用食品包裝\n- T6.1 訂定預防保修計畫\n- T6.2 製定保修作業排程\n- T6.3 執行保修計畫\n- T7.1 優化生產製程\n- T7.2 實施改善\n\n四、職能要求\n- 知識項目：10項\n- 技能項目：21項\n- 態度項目：5項\n\n五、建議條件\n大專以上食品相關科系畢業，且具1年以上食品加工生產相關經歷或高中（職）以上相關科系畢業，且具3年以上食品加工生產相關經歷。",
      "metadata": {
        "code": "NFP7919-002v4",
        "name": "規劃與協調製程管理維",
        "chunk_type": "summary"
      }
    }
  ],
  "parse_success": true,
  "parse_errors": []
}